{
  "a_comp_cor_00": {
    "CumulativeVarianceExplained": 0.0265492608,
    "Mask": "combined",
    "Method": "aCompCor",
    "Retained": true,
    "SingularValue": 80.6673652875,
    "VarianceExplained": 0.0265492608
  },
  "a_comp_cor_01": {
    "CumulativeVarianceExplained": 0.0510393126,
    "Mask": "combined",
    "Method": "aCompCor",
    "Retained": true,
    "SingularValue": 77.4758780951,
    "VarianceExplained": 0.0244900518
  },
  "a_comp_cor_02": {
    "CumulativeVarianceExplained": 0.0739021794,
    "Mask": "combined",
    "Method": "aCompCor",
    "Retained": true,
    "SingularValue": 74.8577895841,
    "VarianceExplained": 0.0228628668
  },
  "a_comp_cor_03": {
    "CumulativeVarianceExplained": 0.0915238942,
    "Mask": "combined",
    "Method": "aCompCor",
    "Retained": true,
    "SingularValue": 65.7197253376,
    "VarianceExplained": 0.0176217148
  },
  "a_comp_cor_04": {
    "CumulativeVarianceExplained": 0.1039577896,
    "Mask": "combined",
    "Method": "aCompCor",
    "Retained": true,
    "SingularValue": 55.2045991985,
    "VarianceExplained": 0.0124338954
  },
  "a_comp_cor_05": {
    "CumulativeVarianceExplained": 0.1155474818,
    "Mask": "combined",
    "Method": "aCompCor",
    "Retained": true,
    "SingularValue": 53.2975942518,
    "VarianceExplained": 0.0115896922
  },
  "a_comp_cor_06": {
    "CumulativeVarianceExplained": 0.1267368796,
    "Mask": "combined",
    "Method": "aCompCor",
    "Retained": true,
    "SingularValue": 52.3690882491,
    "VarianceExplained": 0.0111893978
  },
  "a_comp_cor_07": {
    "CumulativeVarianceExplained": 0.1378105266,
    "Mask": "combined",
    "Method": "aCompCor",
    "Retained": true,
    "SingularValue": 52.0975130518,
    "VarianceExplained": 0.0110736469
  },
  "a_comp_cor_08": {
    "CumulativeVarianceExplained": 0.1486886983,
    "Mask": "combined",
    "Method": "aCompCor",
    "Retained": true,
    "SingularValue": 51.635645565,
    "VarianceExplained": 0.0108781717
  },
  "a_comp_cor_09": {
    "CumulativeVarianceExplained": 0.1592783757,
    "Mask": "combined",
    "Method": "aCompCor",
    "Retained": true,
    "SingularValue": 50.9463436552,
    "VarianceExplained": 0.0105896774
  },
  "a_comp_cor_10": {
    "CumulativeVarianceExplained": 0.1696444905,
    "Mask": "combined",
    "Method": "aCompCor",
    "Retained": true,
    "SingularValue": 50.4057012709,
    "VarianceExplained": 0.0103661147
  },
  "a_comp_cor_11": {
    "CumulativeVarianceExplained": 0.1799482644,
    "Mask": "combined",
    "Method": "aCompCor",
    "Retained": true,
    "SingularValue": 50.2539051612,
    "VarianceExplained": 0.0103037739
  },
  "a_comp_cor_12": {
    "CumulativeVarianceExplained": 0.1900773422,
    "Mask": "combined",
    "Method": "aCompCor",
    "Retained": true,
    "SingularValue": 49.8260671558,
    "VarianceExplained": 0.0101290778
  },
  "a_comp_cor_13": {
    "CumulativeVarianceExplained": 0.2001731074,
    "Mask": "combined",
    "Method": "aCompCor",
    "Retained": true,
    "SingularValue": 49.7440654888,
    "VarianceExplained": 0.0100957652
  },
  "a_comp_cor_14": {
    "CumulativeVarianceExplained": 0.2100833961,
    "Mask": "combined",
    "Method": "aCompCor",
    "Retained": true,
    "SingularValue": 49.2850056496,
    "VarianceExplained": 0.0099102888
  },
  "a_comp_cor_15": {
    "CumulativeVarianceExplained": 0.2199022352,
    "Mask": "combined",
    "Method": "aCompCor",
    "Retained": true,
    "SingularValue": 49.0570835143,
    "VarianceExplained": 0.009818839
  },
  "a_comp_cor_16": {
    "CumulativeVarianceExplained": 0.2296107045,
    "Mask": "combined",
    "Method": "aCompCor",
    "Retained": true,
    "SingularValue": 48.7805887832,
    "VarianceExplained": 0.0097084694
  },
  "a_comp_cor_17": {
    "CumulativeVarianceExplained": 0.2392351362,
    "Mask": "combined",
    "Method": "aCompCor",
    "Retained": true,
    "SingularValue": 48.5690045089,
    "VarianceExplained": 0.0096244317
  },
  "a_comp_cor_18": {
    "CumulativeVarianceExplained": 0.248745858,
    "Mask": "combined",
    "Method": "aCompCor",
    "Retained": true,
    "SingularValue": 48.2812376569,
    "VarianceExplained": 0.0095107218
  },
  "a_comp_cor_19": {
    "CumulativeVarianceExplained": 0.258130653,
    "Mask": "combined",
    "Method": "aCompCor",
    "Retained": true,
    "SingularValue": 47.9605384667,
    "VarianceExplained": 0.009384795
  },
  "a_comp_cor_20": {
    "CumulativeVarianceExplained": 0.2674788105,
    "Mask": "combined",
    "Method": "aCompCor",
    "Retained": true,
    "SingularValue": 47.8668300279,
    "VarianceExplained": 0.0093481576
  },
  "a_comp_cor_21": {
    "CumulativeVarianceExplained": 0.2767731071,
    "Mask": "combined",
    "Method": "aCompCor",
    "Retained": true,
    "SingularValue": 47.7287345477,
    "VarianceExplained": 0.0092942966
  },
  "a_comp_cor_22": {
    "CumulativeVarianceExplained": 0.285937089,
    "Mask": "combined",
    "Method": "aCompCor",
    "Retained": true,
    "SingularValue": 47.3929526163,
    "VarianceExplained": 0.0091639819
  },
  "a_comp_cor_23": {
    "CumulativeVarianceExplained": 0.2950629917,
    "Mask": "combined",
    "Method": "aCompCor",
    "Retained": true,
    "SingularValue": 47.294383819,
    "VarianceExplained": 0.0091259027
  },
  "a_comp_cor_24": {
    "CumulativeVarianceExplained": 0.3041823954,
    "Mask": "combined",
    "Method": "aCompCor",
    "Retained": true,
    "SingularValue": 47.2775408,
    "VarianceExplained": 0.0091194038
  },
  "a_comp_cor_25": {
    "CumulativeVarianceExplained": 0.3131441869,
    "Mask": "combined",
    "Method": "aCompCor",
    "Retained": true,
    "SingularValue": 46.8672070299,
    "VarianceExplained": 0.0089617915
  },
  "a_comp_cor_26": {
    "CumulativeVarianceExplained": 0.3219908132,
    "Mask": "combined",
    "Method": "aCompCor",
    "Retained": true,
    "SingularValue": 46.5650954289,
    "VarianceExplained": 0.0088466263
  },
  "a_comp_cor_27": {
    "CumulativeVarianceExplained": 0.3307544439,
    "Mask": "combined",
    "Method": "aCompCor",
    "Retained": true,
    "SingularValue": 46.3461527802,
    "VarianceExplained": 0.0087636307
  },
  "a_comp_cor_28": {
    "CumulativeVarianceExplained": 0.339439496,
    "Mask": "combined",
    "Method": "aCompCor",
    "Retained": true,
    "SingularValue": 46.1379049448,
    "VarianceExplained": 0.0086850521
  },
  "a_comp_cor_29": {
    "CumulativeVarianceExplained": 0.3479766797,
    "Mask": "combined",
    "Method": "aCompCor",
    "Retained": true,
    "SingularValue": 45.7434555646,
    "VarianceExplained": 0.0085371837
  },
  "a_comp_cor_30": {
    "CumulativeVarianceExplained": 0.356484346,
    "Mask": "combined",
    "Method": "aCompCor",
    "Retained": true,
    "SingularValue": 45.6643077218,
    "VarianceExplained": 0.0085076663
  },
  "a_comp_cor_31": {
    "CumulativeVarianceExplained": 0.3648901413,
    "Mask": "combined",
    "Method": "aCompCor",
    "Retained": true,
    "SingularValue": 45.390091647,
    "VarianceExplained": 0.0084057953
  },
  "a_comp_cor_32": {
    "CumulativeVarianceExplained": 0.3732417558,
    "Mask": "combined",
    "Method": "aCompCor",
    "Retained": true,
    "SingularValue": 45.2435711713,
    "VarianceExplained": 0.0083516146
  },
  "a_comp_cor_33": {
    "CumulativeVarianceExplained": 0.3815792228,
    "Mask": "combined",
    "Method": "aCompCor",
    "Retained": true,
    "SingularValue": 45.2052336956,
    "VarianceExplained": 0.008337467
  },
  "a_comp_cor_34": {
    "CumulativeVarianceExplained": 0.3897912439,
    "Mask": "combined",
    "Method": "aCompCor",
    "Retained": true,
    "SingularValue": 44.8638647791,
    "VarianceExplained": 0.0082120211
  },
  "a_comp_cor_35": {
    "CumulativeVarianceExplained": 0.3979867484,
    "Mask": "combined",
    "Method": "aCompCor",
    "Retained": true,
    "SingularValue": 44.8187254521,
    "VarianceExplained": 0.0081955045
  },
  "a_comp_cor_36": {
    "CumulativeVarianceExplained": 0.4060474212,
    "Mask": "combined",
    "Method": "aCompCor",
    "Retained": true,
    "SingularValue": 44.4485197134,
    "VarianceExplained": 0.0080606728
  },
  "a_comp_cor_37": {
    "CumulativeVarianceExplained": 0.4140443777,
    "Mask": "combined",
    "Method": "aCompCor",
    "Retained": true,
    "SingularValue": 44.2724974838,
    "VarianceExplained": 0.0079969565
  },
  "a_comp_cor_38": {
    "CumulativeVarianceExplained": 0.4220027762,
    "Mask": "combined",
    "Method": "aCompCor",
    "Retained": true,
    "SingularValue": 44.1656368285,
    "VarianceExplained": 0.0079583985
  },
  "a_comp_cor_39": {
    "CumulativeVarianceExplained": 0.4298652654,
    "Mask": "combined",
    "Method": "aCompCor",
    "Retained": true,
    "SingularValue": 43.8987028165,
    "VarianceExplained": 0.0078624892
  },
  "a_comp_cor_40": {
    "CumulativeVarianceExplained": 0.4377091569,
    "Mask": "combined",
    "Method": "aCompCor",
    "Retained": true,
    "SingularValue": 43.8467536432,
    "VarianceExplained": 0.0078438915
  },
  "a_comp_cor_41": {
    "CumulativeVarianceExplained": 0.445514622,
    "Mask": "combined",
    "Method": "aCompCor",
    "Retained": true,
    "SingularValue": 43.739221614,
    "VarianceExplained": 0.0078054651
  },
  "a_comp_cor_42": {
    "CumulativeVarianceExplained": 0.4532215126,
    "Mask": "combined",
    "Method": "aCompCor",
    "Retained": true,
    "SingularValue": 43.462154535,
    "VarianceExplained": 0.0077068906
  },
  "a_comp_cor_43": {
    "CumulativeVarianceExplained": 0.4608856282,
    "Mask": "combined",
    "Method": "aCompCor",
    "Retained": true,
    "SingularValue": 43.3413744365,
    "VarianceExplained": 0.0076641156
  },
  "a_comp_cor_44": {
    "CumulativeVarianceExplained": 0.4685251715,
    "Mask": "combined",
    "Method": "aCompCor",
    "Retained": true,
    "SingularValue": 43.2718390844,
    "VarianceExplained": 0.0076395433
  },
  "a_comp_cor_45": {
    "CumulativeVarianceExplained": 0.4761144975,
    "Mask": "combined",
    "Method": "aCompCor",
    "Retained": true,
    "SingularValue": 43.1293844442,
    "VarianceExplained": 0.007589326
  },
  "a_comp_cor_46": {
    "CumulativeVarianceExplained": 0.4836121584,
    "Mask": "combined",
    "Method": "aCompCor",
    "Retained": true,
    "SingularValue": 42.8681312777,
    "VarianceExplained": 0.0074976609
  },
  "a_comp_cor_47": {
    "CumulativeVarianceExplained": 0.4910758567,
    "Mask": "combined",
    "Method": "aCompCor",
    "Retained": true,
    "SingularValue": 42.770930243,
    "VarianceExplained": 0.0074636984
  },
  "a_comp_cor_48": {
    "CumulativeVarianceExplained": 0.4984753214,
    "Mask": "combined",
    "Method": "aCompCor",
    "Retained": true,
    "SingularValue": 42.5864858667,
    "VarianceExplained": 0.0073994646
  },
  "a_comp_cor_49": {
    "CumulativeVarianceExplained": 0.5058219543,
    "Mask": "combined",
    "Method": "aCompCor",
    "Retained": true,
    "SingularValue": 42.434181054,
    "VarianceExplained": 0.0073466329
  },
  "c_comp_cor_00": {
    "CumulativeVarianceExplained": 0.1798195166,
    "Mask": "CSF",
    "Method": "aCompCor",
    "Retained": true,
    "SingularValue": 70.2569977375,
    "VarianceExplained": 0.1798195166
  },
  "c_comp_cor_01": {
    "CumulativeVarianceExplained": 0.2728697192,
    "Mask": "CSF",
    "Method": "aCompCor",
    "Retained": true,
    "SingularValue": 50.5393713982,
    "VarianceExplained": 0.0930502026
  },
  "c_comp_cor_02": {
    "CumulativeVarianceExplained": 0.3232728952,
    "Mask": "CSF",
    "Method": "aCompCor",
    "Retained": true,
    "SingularValue": 37.1963328938,
    "VarianceExplained": 0.050403176
  },
  "c_comp_cor_03": {
    "CumulativeVarianceExplained": 0.3676067968,
    "Mask": "CSF",
    "Method": "aCompCor",
    "Retained": true,
    "SingularValue": 34.8850340256,
    "VarianceExplained": 0.0443339016
  },
  "c_comp_cor_04": {
    "CumulativeVarianceExplained": 0.4006553342,
    "Mask": "CSF",
    "Method": "aCompCor",
    "Retained": true,
    "SingularValue": 30.1194679703,
    "VarianceExplained": 0.0330485374
  },
  "c_comp_cor_05": {
    "CumulativeVarianceExplained": 0.4287180267,
    "Mask": "CSF",
    "Method": "aCompCor",
    "Retained": true,
    "SingularValue": 27.7546556466,
    "VarianceExplained": 0.0280626925
  },
  "c_comp_cor_06": {
    "CumulativeVarianceExplained": 0.4522279812,
    "Mask": "CSF",
    "Method": "aCompCor",
    "Retained": true,
    "SingularValue": 25.4037054411,
    "VarianceExplained": 0.0235099545
  },
  "c_comp_cor_07": {
    "CumulativeVarianceExplained": 0.475325545,
    "Mask": "CSF",
    "Method": "aCompCor",
    "Retained": true,
    "SingularValue": 25.1799151573,
    "VarianceExplained": 0.0230975638
  },
  "c_comp_cor_08": {
    "CumulativeVarianceExplained": 0.4944992095,
    "Mask": "CSF",
    "Method": "aCompCor",
    "Retained": true,
    "SingularValue": 22.9416017523,
    "VarianceExplained": 0.0191736645
  },
  "c_comp_cor_09": {
    "CumulativeVarianceExplained": 0.5132878048,
    "Mask": "CSF",
    "Method": "aCompCor",
    "Retained": true,
    "SingularValue": 22.710062513,
    "VarianceExplained": 0.0187885952
  },
  "dropped_0": {
    "CumulativeVarianceExplained": 0.3120303579,
    "Mask": "Edge",
    "Method": "EdgeRegressor",
    "Retained": false,
    "SingularValue": 107.9327710466,
    "VarianceExplained": 0.0071198405
  },
  "dropped_1": {
    "CumulativeVarianceExplained": 0.3191346206,
    "Mask": "Edge",
    "Method": "EdgeRegressor",
    "Retained": false,
    "SingularValue": 107.8146314568,
    "VarianceExplained": 0.0071042628
  },
  "dropped_10": {
    "CumulativeVarianceExplained": 0.380923886,
    "Mask": "Edge",
    "Method": "EdgeRegressor",
    "Retained": false,
    "SingularValue": 104.968896122,
    "VarianceExplained": 0.0067341823
  },
  "dropped_100": {
    "CumulativeVarianceExplained": 0.9026431434,
    "Mask": "Edge",
    "Method": "EdgeRegressor",
    "Retained": false,
    "SingularValue": 90.5043186983,
    "VarianceExplained": 0.0050061311
  },
  "dropped_101": {
    "CumulativeVarianceExplained": 0.9076226659,
    "Mask": "Edge",
    "Method": "EdgeRegressor",
    "Retained": false,
    "SingularValue": 90.2634736868,
    "VarianceExplained": 0.0049795225
  },
  "dropped_102": {
    "CumulativeVarianceExplained": 0.912596294,
    "Mask": "Edge",
    "Method": "EdgeRegressor",
    "Retained": false,
    "SingularValue": 90.2100338397,
    "VarianceExplained": 0.004973628
  },
  "dropped_103": {
    "CumulativeVarianceExplained": 0.9175148645,
    "Mask": "Edge",
    "Method": "EdgeRegressor",
    "Retained": false,
    "SingularValue": 89.7093366945,
    "VarianceExplained": 0.0049185705
  },
  "dropped_104": {
    "CumulativeVarianceExplained": 0.922429817,
    "Mask": "Edge",
    "Method": "EdgeRegressor",
    "Retained": false,
    "SingularValue": 89.6763362142,
    "VarianceExplained": 0.0049149525
  },
  "dropped_105": {
    "CumulativeVarianceExplained": 0.927331098,
    "Mask": "Edge",
    "Method": "EdgeRegressor",
    "Retained": false,
    "SingularValue": 89.5515268182,
    "VarianceExplained": 0.004901281
  },
  "dropped_106": {
    "CumulativeVarianceExplained": 0.9322061268,
    "Mask": "Edge",
    "Method": "EdgeRegressor",
    "Retained": false,
    "SingularValue": 89.3113778064,
    "VarianceExplained": 0.0048750289
  },
  "dropped_107": {
    "CumulativeVarianceExplained": 0.9370439327,
    "Mask": "Edge",
    "Method": "EdgeRegressor",
    "Retained": false,
    "SingularValue": 88.9697588191,
    "VarianceExplained": 0.0048378059
  },
  "dropped_108": {
    "CumulativeVarianceExplained": 0.9418712624,
    "Mask": "Edge",
    "Method": "EdgeRegressor",
    "Retained": false,
    "SingularValue": 88.8733752887,
    "VarianceExplained": 0.0048273297
  },
  "dropped_109": {
    "CumulativeVarianceExplained": 0.9466783523,
    "Mask": "Edge",
    "Method": "EdgeRegressor",
    "Retained": false,
    "SingularValue": 88.6868680673,
    "VarianceExplained": 0.0048070899
  },
  "dropped_11": {
    "CumulativeVarianceExplained": 0.3876412156,
    "Mask": "Edge",
    "Method": "EdgeRegressor",
    "Retained": false,
    "SingularValue": 104.837467927,
    "VarianceExplained": 0.0067173296
  },
  "dropped_110": {
    "CumulativeVarianceExplained": 0.9514612116,
    "Mask": "Edge",
    "Method": "EdgeRegressor",
    "Retained": false,
    "SingularValue": 88.4630674719,
    "VarianceExplained": 0.0047828593
  },
  "dropped_111": {
    "CumulativeVarianceExplained": 0.9562130473,
    "Mask": "Edge",
    "Method": "EdgeRegressor",
    "Retained": false,
    "SingularValue": 88.1756970921,
    "VarianceExplained": 0.0047518357
  },
  "dropped_112": {
    "CumulativeVarianceExplained": 0.9609543526,
    "Mask": "Edge",
    "Method": "EdgeRegressor",
    "Retained": false,
    "SingularValue": 88.0779416648,
    "VarianceExplained": 0.0047413053
  },
  "dropped_113": {
    "CumulativeVarianceExplained": 0.9656770746,
    "Mask": "Edge",
    "Method": "EdgeRegressor",
    "Retained": false,
    "SingularValue": 87.9051632792,
    "VarianceExplained": 0.004722722
  },
  "dropped_114": {
    "CumulativeVarianceExplained": 0.9703553525,
    "Mask": "Edge",
    "Method": "EdgeRegressor",
    "Retained": false,
    "SingularValue": 87.4905610296,
    "VarianceExplained": 0.0046782779
  },
  "dropped_115": {
    "CumulativeVarianceExplained": 0.9750303548,
    "Mask": "Edge",
    "Method": "EdgeRegressor",
    "Retained": false,
    "SingularValue": 87.4599270154,
    "VarianceExplained": 0.0046750023
  },
  "dropped_116": {
    "CumulativeVarianceExplained": 0.979636825,
    "Mask": "Edge",
    "Method": "EdgeRegressor",
    "Retained": false,
    "SingularValue": 86.816510247,
    "VarianceExplained": 0.0046064701
  },
  "dropped_117": {
    "CumulativeVarianceExplained": 0.9842270028,
    "Mask": "Edge",
    "Method": "EdgeRegressor",
    "Retained": false,
    "SingularValue": 86.6628459471,
    "VarianceExplained": 0.0045901778
  },
  "dropped_118": {
    "CumulativeVarianceExplained": 0.9887975373,
    "Mask": "Edge",
    "Method": "EdgeRegressor",
    "Retained": false,
    "SingularValue": 86.4772139608,
    "VarianceExplained": 0.0045705345
  },
  "dropped_119": {
    "CumulativeVarianceExplained": 0.9933091361,
    "Mask": "Edge",
    "Method": "EdgeRegressor",
    "Retained": false,
    "SingularValue": 85.9178560493,
    "VarianceExplained": 0.0045115988
  },
  "dropped_12": {
    "CumulativeVarianceExplained": 0.3943377659,
    "Mask": "Edge",
    "Method": "EdgeRegressor",
    "Retained": false,
    "SingularValue": 104.6751911683,
    "VarianceExplained": 0.0066965503
  },
  "dropped_120": {
    "CumulativeVarianceExplained": 0.9972664268,
    "Mask": "Edge",
    "Method": "EdgeRegressor",
    "Retained": false,
    "SingularValue": 80.4668816364,
    "VarianceExplained": 0.0039572907
  },
  "dropped_121": {
    "CumulativeVarianceExplained": 1.0,
    "Mask": "Edge",
    "Method": "EdgeRegressor",
    "Retained": false,
    "SingularValue": 66.8780421041,
    "VarianceExplained": 0.0027335732
  },
  "dropped_122": {
    "CumulativeVarianceExplained": 1.0,
    "Mask": "Edge",
    "Method": "EdgeRegressor",
    "Retained": false,
    "SingularValue": 0.0,
    "VarianceExplained": 0.0
  },
  "dropped_123": {
    "CumulativeVarianceExplained": 1.0,
    "Mask": "Edge",
    "Method": "EdgeRegressor",
    "Retained": false,
    "SingularValue": 0.0,
    "VarianceExplained": 0.0
  },
  "dropped_124": {
    "CumulativeVarianceExplained": 1.0,
    "Mask": "Edge",
    "Method": "EdgeRegressor",
    "Retained": false,
    "SingularValue": 0.0,
    "VarianceExplained": 0.0
  },
  "dropped_125": {
    "CumulativeVarianceExplained": 1.0,
    "Mask": "Edge",
    "Method": "EdgeRegressor",
    "Retained": false,
    "SingularValue": 0.0,
    "VarianceExplained": 0.0
  },
  "dropped_13": {
    "CumulativeVarianceExplained": 0.4010163938,
    "Mask": "Edge",
    "Method": "EdgeRegressor",
    "Retained": false,
    "SingularValue": 104.5350226851,
    "VarianceExplained": 0.0066786279
  },
  "dropped_14": {
    "CumulativeVarianceExplained": 0.4076417122,
    "Mask": "Edge",
    "Method": "EdgeRegressor",
    "Retained": false,
    "SingularValue": 104.1169826176,
    "VarianceExplained": 0.0066253185
  },
  "dropped_15": {
    "CumulativeVarianceExplained": 0.4142616785,
    "Mask": "Edge",
    "Method": "EdgeRegressor",
    "Retained": false,
    "SingularValue": 104.0749193557,
    "VarianceExplained": 0.0066199663
  },
  "dropped_16": {
    "CumulativeVarianceExplained": 0.420840629,
    "Mask": "Edge",
    "Method": "EdgeRegressor",
    "Retained": false,
    "SingularValue": 103.7520059357,
    "VarianceExplained": 0.0065789505
  },
  "dropped_17": {
    "CumulativeVarianceExplained": 0.4274019122,
    "Mask": "Edge",
    "Method": "EdgeRegressor",
    "Retained": false,
    "SingularValue": 103.6126037992,
    "VarianceExplained": 0.0065612833
  },
  "dropped_18": {
    "CumulativeVarianceExplained": 0.4339078068,
    "Mask": "Edge",
    "Method": "EdgeRegressor",
    "Retained": false,
    "SingularValue": 103.1743413687,
    "VarianceExplained": 0.0065058946
  },
  "dropped_19": {
    "CumulativeVarianceExplained": 0.4403938412,
    "Mask": "Edge",
    "Method": "EdgeRegressor",
    "Retained": false,
    "SingularValue": 103.0167432476,
    "VarianceExplained": 0.0064860343
  },
  "dropped_2": {
    "CumulativeVarianceExplained": 0.3261428101,
    "Mask": "Edge",
    "Method": "EdgeRegressor",
    "Retained": false,
    "SingularValue": 107.0831430744,
    "VarianceExplained": 0.0070081894
  },
  "dropped_20": {
    "CumulativeVarianceExplained": 0.44686384,
    "Mask": "Edge",
    "Method": "EdgeRegressor",
    "Retained": false,
    "SingularValue": 102.8893191589,
    "VarianceExplained": 0.0064699988
  },
  "dropped_21": {
    "CumulativeVarianceExplained": 0.4533173003,
    "Mask": "Edge",
    "Method": "EdgeRegressor",
    "Retained": false,
    "SingularValue": 102.757733794,
    "VarianceExplained": 0.0064534604
  },
  "dropped_22": {
    "CumulativeVarianceExplained": 0.4597550302,
    "Mask": "Edge",
    "Method": "EdgeRegressor",
    "Retained": false,
    "SingularValue": 102.6324198671,
    "VarianceExplained": 0.0064377299
  },
  "dropped_23": {
    "CumulativeVarianceExplained": 0.4661572884,
    "Mask": "Edge",
    "Method": "EdgeRegressor",
    "Retained": false,
    "SingularValue": 102.3492792759,
    "VarianceExplained": 0.0064022583
  },
  "dropped_24": {
    "CumulativeVarianceExplained": 0.4725462771,
    "Mask": "Edge",
    "Method": "EdgeRegressor",
    "Retained": false,
    "SingularValue": 102.2431574668,
    "VarianceExplained": 0.0063889887
  },
  "dropped_25": {
    "CumulativeVarianceExplained": 0.4788918495,
    "Mask": "Edge",
    "Method": "EdgeRegressor",
    "Retained": false,
    "SingularValue": 101.8951694652,
    "VarianceExplained": 0.0063455724
  },
  "dropped_26": {
    "CumulativeVarianceExplained": 0.4852172289,
    "Mask": "Edge",
    "Method": "EdgeRegressor",
    "Retained": false,
    "SingularValue": 101.7329136092,
    "VarianceExplained": 0.0063253794
  },
  "dropped_27": {
    "CumulativeVarianceExplained": 0.4915147141,
    "Mask": "Edge",
    "Method": "EdgeRegressor",
    "Retained": false,
    "SingularValue": 101.5083512795,
    "VarianceExplained": 0.0062974853
  },
  "dropped_28": {
    "CumulativeVarianceExplained": 0.4977892806,
    "Mask": "Edge",
    "Method": "EdgeRegressor",
    "Retained": false,
    "SingularValue": 101.3234705297,
    "VarianceExplained": 0.0062745665
  },
  "dropped_29": {
    "CumulativeVarianceExplained": 0.5040477076,
    "Mask": "Edge",
    "Method": "EdgeRegressor",
    "Retained": false,
    "SingularValue": 101.1930743949,
    "VarianceExplained": 0.006258427
  },
  "dropped_3": {
    "CumulativeVarianceExplained": 0.3331324057,
    "Mask": "Edge",
    "Method": "EdgeRegressor",
    "Retained": false,
    "SingularValue": 106.9409948146,
    "VarianceExplained": 0.0069895956
  },
  "dropped_30": {
    "CumulativeVarianceExplained": 0.5102972535,
    "Mask": "Edge",
    "Method": "EdgeRegressor",
    "Retained": false,
    "SingularValue": 101.121248734,
    "VarianceExplained": 0.0062495459
  },
  "dropped_31": {
    "CumulativeVarianceExplained": 0.5165299506,
    "Mask": "Edge",
    "Method": "EdgeRegressor",
    "Retained": false,
    "SingularValue": 100.9848452535,
    "VarianceExplained": 0.0062326971
  },
  "dropped_32": {
    "CumulativeVarianceExplained": 0.5227464225,
    "Mask": "Edge",
    "Method": "EdgeRegressor",
    "Retained": false,
    "SingularValue": 100.8533162072,
    "VarianceExplained": 0.0062164719
  },
  "dropped_33": {
    "CumulativeVarianceExplained": 0.5289432428,
    "Mask": "Edge",
    "Method": "EdgeRegressor",
    "Retained": false,
    "SingularValue": 100.6937802103,
    "VarianceExplained": 0.0061968203
  },
  "dropped_34": {
    "CumulativeVarianceExplained": 0.5351071309,
    "Mask": "Edge",
    "Method": "EdgeRegressor",
    "Retained": false,
    "SingularValue": 100.4258611898,
    "VarianceExplained": 0.006163888
  },
  "dropped_35": {
    "CumulativeVarianceExplained": 0.5412644249,
    "Mask": "Edge",
    "Method": "EdgeRegressor",
    "Retained": false,
    "SingularValue": 100.3721303284,
    "VarianceExplained": 0.0061572941
  },
  "dropped_36": {
    "CumulativeVarianceExplained": 0.5474037279,
    "Mask": "Edge",
    "Method": "EdgeRegressor",
    "Retained": false,
    "SingularValue": 100.2253833984,
    "VarianceExplained": 0.0061393029
  },
  "dropped_37": {
    "CumulativeVarianceExplained": 0.5535201922,
    "Mask": "Edge",
    "Method": "EdgeRegressor",
    "Retained": false,
    "SingularValue": 100.0387872947,
    "VarianceExplained": 0.0061164643
  },
  "dropped_38": {
    "CumulativeVarianceExplained": 0.5596254341,
    "Mask": "Edge",
    "Method": "EdgeRegressor",
    "Retained": false,
    "SingularValue": 99.9469697079,
    "VarianceExplained": 0.0061052419
  },
  "dropped_39": {
    "CumulativeVarianceExplained": 0.5657162821,
    "Mask": "Edge",
    "Method": "EdgeRegressor",
    "Retained": false,
    "SingularValue": 99.8290816628,
    "VarianceExplained": 0.006090848
  },
  "dropped_4": {
    "CumulativeVarianceExplained": 0.3400822386,
    "Mask": "Edge",
    "Method": "EdgeRegressor",
    "Retained": false,
    "SingularValue": 106.63637585,
    "VarianceExplained": 0.0069498329
  },
  "dropped_40": {
    "CumulativeVarianceExplained": 0.5717775184,
    "Mask": "Edge",
    "Method": "EdgeRegressor",
    "Retained": false,
    "SingularValue": 99.5861176032,
    "VarianceExplained": 0.0060612363
  },
  "dropped_41": {
    "CumulativeVarianceExplained": 0.5778336972,
    "Mask": "Edge",
    "Method": "EdgeRegressor",
    "Retained": false,
    "SingularValue": 99.5445619244,
    "VarianceExplained": 0.0060561788
  },
  "dropped_42": {
    "CumulativeVarianceExplained": 0.5838449851,
    "Mask": "Edge",
    "Method": "EdgeRegressor",
    "Retained": false,
    "SingularValue": 99.1749422833,
    "VarianceExplained": 0.0060112878
  },
  "dropped_43": {
    "CumulativeVarianceExplained": 0.5898410934,
    "Mask": "Edge",
    "Method": "EdgeRegressor",
    "Retained": false,
    "SingularValue": 99.0496462913,
    "VarianceExplained": 0.0059961083
  },
  "dropped_44": {
    "CumulativeVarianceExplained": 0.5958321602,
    "Mask": "Edge",
    "Method": "EdgeRegressor",
    "Retained": false,
    "SingularValue": 99.0079967819,
    "VarianceExplained": 0.0059910668
  },
  "dropped_45": {
    "CumulativeVarianceExplained": 0.6017915851,
    "Mask": "Edge",
    "Method": "EdgeRegressor",
    "Retained": false,
    "SingularValue": 98.7461950224,
    "VarianceExplained": 0.0059594249
  },
  "dropped_46": {
    "CumulativeVarianceExplained": 0.6077419936,
    "Mask": "Edge",
    "Method": "EdgeRegressor",
    "Retained": false,
    "SingularValue": 98.6714667893,
    "VarianceExplained": 0.0059504085
  },
  "dropped_47": {
    "CumulativeVarianceExplained": 0.6136597349,
    "Mask": "Edge",
    "Method": "EdgeRegressor",
    "Retained": false,
    "SingularValue": 98.4002459832,
    "VarianceExplained": 0.0059177414
  },
  "dropped_48": {
    "CumulativeVarianceExplained": 0.6195677678,
    "Mask": "Edge",
    "Method": "EdgeRegressor",
    "Retained": false,
    "SingularValue": 98.3194968885,
    "VarianceExplained": 0.0059080329
  },
  "dropped_49": {
    "CumulativeVarianceExplained": 0.6254647892,
    "Mask": "Edge",
    "Method": "EdgeRegressor",
    "Retained": false,
    "SingularValue": 98.2278285054,
    "VarianceExplained": 0.0058970213
  },
  "dropped_5": {
    "CumulativeVarianceExplained": 0.3469797339,
    "Mask": "Edge",
    "Method": "EdgeRegressor",
    "Retained": false,
    "SingularValue": 106.2340893244,
    "VarianceExplained": 0.0068974953
  },
  "dropped_50": {
    "CumulativeVarianceExplained": 0.6313403169,
    "Mask": "Edge",
    "Method": "EdgeRegressor",
    "Retained": false,
    "SingularValue": 98.0486537221,
    "VarianceExplained": 0.0058755277
  },
  "dropped_51": {
    "CumulativeVarianceExplained": 0.6371973681,
    "Mask": "Edge",
    "Method": "EdgeRegressor",
    "Retained": false,
    "SingularValue": 97.8943674773,
    "VarianceExplained": 0.0058570512
  },
  "dropped_52": {
    "CumulativeVarianceExplained": 0.6430392409,
    "Mask": "Edge",
    "Method": "EdgeRegressor",
    "Retained": false,
    "SingularValue": 97.7674397762,
    "VarianceExplained": 0.0058418728
  },
  "dropped_53": {
    "CumulativeVarianceExplained": 0.6488684003,
    "Mask": "Edge",
    "Method": "EdgeRegressor",
    "Retained": false,
    "SingularValue": 97.6609986163,
    "VarianceExplained": 0.0058291594
  },
  "dropped_54": {
    "CumulativeVarianceExplained": 0.6546862551,
    "Mask": "Edge",
    "Method": "EdgeRegressor",
    "Retained": false,
    "SingularValue": 97.5662541927,
    "VarianceExplained": 0.0058178548
  },
  "dropped_55": {
    "CumulativeVarianceExplained": 0.6604683723,
    "Mask": "Edge",
    "Method": "EdgeRegressor",
    "Retained": false,
    "SingularValue": 97.2661307067,
    "VarianceExplained": 0.0057821172
  },
  "dropped_56": {
    "CumulativeVarianceExplained": 0.6662293148,
    "Mask": "Edge",
    "Method": "EdgeRegressor",
    "Retained": false,
    "SingularValue": 97.0878679918,
    "VarianceExplained": 0.0057609425
  },
  "dropped_57": {
    "CumulativeVarianceExplained": 0.6719832634,
    "Mask": "Edge",
    "Method": "EdgeRegressor",
    "Retained": false,
    "SingularValue": 97.0289167912,
    "VarianceExplained": 0.0057539486
  },
  "dropped_58": {
    "CumulativeVarianceExplained": 0.6777138053,
    "Mask": "Edge",
    "Method": "EdgeRegressor",
    "Retained": false,
    "SingularValue": 96.8313616363,
    "VarianceExplained": 0.0057305419
  },
  "dropped_59": {
    "CumulativeVarianceExplained": 0.6834202476,
    "Mask": "Edge",
    "Method": "EdgeRegressor",
    "Retained": false,
    "SingularValue": 96.6275369718,
    "VarianceExplained": 0.0057064423
  },
  "dropped_6": {
    "CumulativeVarianceExplained": 0.3538241761,
    "Mask": "Edge",
    "Method": "EdgeRegressor",
    "Retained": false,
    "SingularValue": 105.8247434452,
    "VarianceExplained": 0.0068444422
  },
  "dropped_60": {
    "CumulativeVarianceExplained": 0.6891181984,
    "Mask": "Edge",
    "Method": "EdgeRegressor",
    "Retained": false,
    "SingularValue": 96.55561666,
    "VarianceExplained": 0.0056979508
  },
  "dropped_61": {
    "CumulativeVarianceExplained": 0.6948098906,
    "Mask": "Edge",
    "Method": "EdgeRegressor",
    "Retained": false,
    "SingularValue": 96.5025739137,
    "VarianceExplained": 0.0056916922
  },
  "dropped_62": {
    "CumulativeVarianceExplained": 0.7004839474,
    "Mask": "Edge",
    "Method": "EdgeRegressor",
    "Retained": false,
    "SingularValue": 96.3529544187,
    "VarianceExplained": 0.0056740569
  },
  "dropped_63": {
    "CumulativeVarianceExplained": 0.7061451931,
    "Mask": "Edge",
    "Method": "EdgeRegressor",
    "Retained": false,
    "SingularValue": 96.2441177304,
    "VarianceExplained": 0.0056612457
  },
  "dropped_64": {
    "CumulativeVarianceExplained": 0.7117824596,
    "Mask": "Edge",
    "Method": "EdgeRegressor",
    "Retained": false,
    "SingularValue": 96.040072064,
    "VarianceExplained": 0.0056372665
  },
  "dropped_65": {
    "CumulativeVarianceExplained": 0.7174044536,
    "Mask": "Edge",
    "Method": "EdgeRegressor",
    "Retained": false,
    "SingularValue": 95.9098872989,
    "VarianceExplained": 0.0056219939
  },
  "dropped_66": {
    "CumulativeVarianceExplained": 0.7229796688,
    "Mask": "Edge",
    "Method": "EdgeRegressor",
    "Retained": false,
    "SingularValue": 95.5100374231,
    "VarianceExplained": 0.0055752153
  },
  "dropped_67": {
    "CumulativeVarianceExplained": 0.7285480273,
    "Mask": "Edge",
    "Method": "EdgeRegressor",
    "Retained": false,
    "SingularValue": 95.4512866191,
    "VarianceExplained": 0.0055683585
  },
  "dropped_68": {
    "CumulativeVarianceExplained": 0.7340904638,
    "Mask": "Edge",
    "Method": "EdgeRegressor",
    "Retained": false,
    "SingularValue": 95.2288539764,
    "VarianceExplained": 0.0055424365
  },
  "dropped_69": {
    "CumulativeVarianceExplained": 0.7396241316,
    "Mask": "Edge",
    "Method": "EdgeRegressor",
    "Retained": false,
    "SingularValue": 95.1534931476,
    "VarianceExplained": 0.0055336678
  },
  "dropped_7": {
    "CumulativeVarianceExplained": 0.3606493373,
    "Mask": "Edge",
    "Method": "EdgeRegressor",
    "Retained": false,
    "SingularValue": 105.6755826563,
    "VarianceExplained": 0.0068251612
  },
  "dropped_70": {
    "CumulativeVarianceExplained": 0.7451469419,
    "Mask": "Edge",
    "Method": "EdgeRegressor",
    "Retained": false,
    "SingularValue": 95.0600974423,
    "VarianceExplained": 0.0055228102
  },
  "dropped_71": {
    "CumulativeVarianceExplained": 0.750645457,
    "Mask": "Edge",
    "Method": "EdgeRegressor",
    "Retained": false,
    "SingularValue": 94.8507800999,
    "VarianceExplained": 0.0054985151
  },
  "dropped_72": {
    "CumulativeVarianceExplained": 0.7561395292,
    "Mask": "Edge",
    "Method": "EdgeRegressor",
    "Retained": false,
    "SingularValue": 94.812450832,
    "VarianceExplained": 0.0054940721
  },
  "dropped_73": {
    "CumulativeVarianceExplained": 0.761606861,
    "Mask": "Edge",
    "Method": "EdgeRegressor",
    "Retained": false,
    "SingularValue": 94.5814377492,
    "VarianceExplained": 0.0054673318
  },
  "dropped_74": {
    "CumulativeVarianceExplained": 0.7670432049,
    "Mask": "Edge",
    "Method": "EdgeRegressor",
    "Retained": false,
    "SingularValue": 94.3130204158,
    "VarianceExplained": 0.0054363439
  },
  "dropped_75": {
    "CumulativeVarianceExplained": 0.7724630584,
    "Mask": "Edge",
    "Method": "EdgeRegressor",
    "Retained": false,
    "SingularValue": 94.1698698221,
    "VarianceExplained": 0.0054198536
  },
  "dropped_76": {
    "CumulativeVarianceExplained": 0.7778740943,
    "Mask": "Edge",
    "Method": "EdgeRegressor",
    "Retained": false,
    "SingularValue": 94.0932348138,
    "VarianceExplained": 0.0054110358
  },
  "dropped_77": {
    "CumulativeVarianceExplained": 0.7832786143,
    "Mask": "Edge",
    "Method": "EdgeRegressor",
    "Retained": false,
    "SingularValue": 94.0365657205,
    "VarianceExplained": 0.00540452
  },
  "dropped_78": {
    "CumulativeVarianceExplained": 0.7886658342,
    "Mask": "Edge",
    "Method": "EdgeRegressor",
    "Retained": false,
    "SingularValue": 93.8859371074,
    "VarianceExplained": 0.0053872199
  },
  "dropped_79": {
    "CumulativeVarianceExplained": 0.7940391777,
    "Mask": "Edge",
    "Method": "EdgeRegressor",
    "Retained": false,
    "SingularValue": 93.7649440697,
    "VarianceExplained": 0.0053733436
  },
  "dropped_8": {
    "CumulativeVarianceExplained": 0.3674251586,
    "Mask": "Edge",
    "Method": "EdgeRegressor",
    "Retained": false,
    "SingularValue": 105.2929194039,
    "VarianceExplained": 0.0067758213
  },
  "dropped_80": {
    "CumulativeVarianceExplained": 0.7993928503,
    "Mask": "Edge",
    "Method": "EdgeRegressor",
    "Retained": false,
    "SingularValue": 93.5931570722,
    "VarianceExplained": 0.0053536726
  },
  "dropped_81": {
    "CumulativeVarianceExplained": 0.8047447275,
    "Mask": "Edge",
    "Method": "EdgeRegressor",
    "Retained": false,
    "SingularValue": 93.5774620985,
    "VarianceExplained": 0.0053518772
  },
  "dropped_82": {
    "CumulativeVarianceExplained": 0.810075322,
    "Mask": "Edge",
    "Method": "EdgeRegressor",
    "Retained": false,
    "SingularValue": 93.3912135533,
    "VarianceExplained": 0.0053305945
  },
  "dropped_83": {
    "CumulativeVarianceExplained": 0.815359988,
    "Mask": "Edge",
    "Method": "EdgeRegressor",
    "Retained": false,
    "SingularValue": 92.9880127399,
    "VarianceExplained": 0.005284666
  },
  "dropped_84": {
    "CumulativeVarianceExplained": 0.8206277224,
    "Mask": "Edge",
    "Method": "EdgeRegressor",
    "Retained": false,
    "SingularValue": 92.8389301851,
    "VarianceExplained": 0.0052677344
  },
  "dropped_85": {
    "CumulativeVarianceExplained": 0.8258756719,
    "Mask": "Edge",
    "Method": "EdgeRegressor",
    "Retained": false,
    "SingularValue": 92.6644216961,
    "VarianceExplained": 0.0052479495
  },
  "dropped_86": {
    "CumulativeVarianceExplained": 0.8311134687,
    "Mask": "Edge",
    "Method": "EdgeRegressor",
    "Retained": false,
    "SingularValue": 92.5747434182,
    "VarianceExplained": 0.0052377968
  },
  "dropped_87": {
    "CumulativeVarianceExplained": 0.8363371685,
    "Mask": "Edge",
    "Method": "EdgeRegressor",
    "Retained": false,
    "SingularValue": 92.4500814,
    "VarianceExplained": 0.0052236998
  },
  "dropped_88": {
    "CumulativeVarianceExplained": 0.8415357697,
    "Mask": "Edge",
    "Method": "EdgeRegressor",
    "Retained": false,
    "SingularValue": 92.227714402,
    "VarianceExplained": 0.0051986012
  },
  "dropped_89": {
    "CumulativeVarianceExplained": 0.8467244303,
    "Mask": "Edge",
    "Method": "EdgeRegressor",
    "Retained": false,
    "SingularValue": 92.1394951204,
    "VarianceExplained": 0.0051886607
  },
  "dropped_9": {
    "CumulativeVarianceExplained": 0.3741897036,
    "Mask": "Edge",
    "Method": "EdgeRegressor",
    "Retained": false,
    "SingularValue": 105.2052684484,
    "VarianceExplained": 0.006764545
  },
  "dropped_90": {
    "CumulativeVarianceExplained": 0.8518898457,
    "Mask": "Edge",
    "Method": "EdgeRegressor",
    "Retained": false,
    "SingularValue": 91.9328700077,
    "VarianceExplained": 0.0051654153
  },
  "dropped_91": {
    "CumulativeVarianceExplained": 0.857034709,
    "Mask": "Edge",
    "Method": "EdgeRegressor",
    "Retained": false,
    "SingularValue": 91.749797383,
    "VarianceExplained": 0.0051448633
  },
  "dropped_92": {
    "CumulativeVarianceExplained": 0.8621624423,
    "Mask": "Edge",
    "Method": "EdgeRegressor",
    "Retained": false,
    "SingularValue": 91.5969285768,
    "VarianceExplained": 0.0051277334
  },
  "dropped_93": {
    "CumulativeVarianceExplained": 0.8672810205,
    "Mask": "Edge",
    "Method": "EdgeRegressor",
    "Retained": false,
    "SingularValue": 91.5151220498,
    "VarianceExplained": 0.0051185781
  },
  "dropped_94": {
    "CumulativeVarianceExplained": 0.8723807077,
    "Mask": "Edge",
    "Method": "EdgeRegressor",
    "Retained": false,
    "SingularValue": 91.3460900538,
    "VarianceExplained": 0.0050996872
  },
  "dropped_95": {
    "CumulativeVarianceExplained": 0.8774634178,
    "Mask": "Edge",
    "Method": "EdgeRegressor",
    "Retained": false,
    "SingularValue": 91.1939161325,
    "VarianceExplained": 0.0050827101
  },
  "dropped_96": {
    "CumulativeVarianceExplained": 0.8825359498,
    "Mask": "Edge",
    "Method": "EdgeRegressor",
    "Retained": false,
    "SingularValue": 91.102562413,
    "VarianceExplained": 0.005072532
  },
  "dropped_97": {
    "CumulativeVarianceExplained": 0.8875816277,
    "Mask": "Edge",
    "Method": "EdgeRegressor",
    "Retained": false,
    "SingularValue": 90.8610925538,
    "VarianceExplained": 0.0050456779
  },
  "dropped_98": {
    "CumulativeVarianceExplained": 0.8926178309,
    "Mask": "Edge",
    "Method": "EdgeRegressor",
    "Retained": false,
    "SingularValue": 90.7757439421,
    "VarianceExplained": 0.0050362032
  },
  "dropped_99": {
    "CumulativeVarianceExplained": 0.8976370123,
    "Mask": "Edge",
    "Method": "EdgeRegressor",
    "Retained": false,
    "SingularValue": 90.6222084539,
    "VarianceExplained": 0.0050191814
  },
  "edge_comp_00": {
    "CumulativeVarianceExplained": 0.0329351946,
    "Mask": "Edge",
    "Method": "EdgeRegressor",
    "Retained": true,
    "SingularValue": 232.1391079561,
    "VarianceExplained": 0.0329351946
  },
  "edge_comp_01": {
    "CumulativeVarianceExplained": 0.0628918336,
    "Mask": "Edge",
    "Method": "EdgeRegressor",
    "Retained": true,
    "SingularValue": 221.3934342835,
    "VarianceExplained": 0.029956639
  },
  "edge_comp_02": {
    "CumulativeVarianceExplained": 0.084774848,
    "Mask": "Edge",
    "Method": "EdgeRegressor",
    "Retained": true,
    "SingularValue": 189.2220601899,
    "VarianceExplained": 0.0218830143
  },
  "edge_comp_03": {
    "CumulativeVarianceExplained": 0.1056372636,
    "Mask": "Edge",
    "Method": "EdgeRegressor",
    "Retained": true,
    "SingularValue": 184.7568253647,
    "VarianceExplained": 0.0208624157
  },
  "edge_comp_04": {
    "CumulativeVarianceExplained": 0.1257787677,
    "Mask": "Edge",
    "Method": "EdgeRegressor",
    "Retained": true,
    "SingularValue": 181.5365774324,
    "VarianceExplained": 0.0201415041
  },
  "edge_comp_05": {
    "CumulativeVarianceExplained": 0.1430023797,
    "Mask": "Edge",
    "Method": "EdgeRegressor",
    "Retained": true,
    "SingularValue": 167.8727908631,
    "VarianceExplained": 0.017223612
  },
  "edge_comp_06": {
    "CumulativeVarianceExplained": 0.1594810002,
    "Mask": "Edge",
    "Method": "EdgeRegressor",
    "Retained": true,
    "SingularValue": 164.2020671939,
    "VarianceExplained": 0.0164786205
  },
  "edge_comp_07": {
    "CumulativeVarianceExplained": 0.1729007672,
    "Mask": "Edge",
    "Method": "EdgeRegressor",
    "Retained": true,
    "SingularValue": 148.1803726044,
    "VarianceExplained": 0.013419767
  },
  "edge_comp_08": {
    "CumulativeVarianceExplained": 0.1830874331,
    "Mask": "Edge",
    "Method": "EdgeRegressor",
    "Retained": true,
    "SingularValue": 129.1023732552,
    "VarianceExplained": 0.0101866659
  },
  "edge_comp_09": {
    "CumulativeVarianceExplained": 0.1930562548,
    "Mask": "Edge",
    "Method": "EdgeRegressor",
    "Retained": true,
    "SingularValue": 127.7144702918,
    "VarianceExplained": 0.0099688216
  },
  "edge_comp_10": {
    "CumulativeVarianceExplained": 0.2025275428,
    "Mask": "Edge",
    "Method": "EdgeRegressor",
    "Retained": true,
    "SingularValue": 124.4866316673,
    "VarianceExplained": 0.009471288
  },
  "edge_comp_11": {
    "CumulativeVarianceExplained": 0.2116785127,
    "Mask": "Edge",
    "Method": "EdgeRegressor",
    "Retained": true,
    "SingularValue": 122.3634627989,
    "VarianceExplained": 0.0091509699
  },
  "edge_comp_12": {
    "CumulativeVarianceExplained": 0.2204397701,
    "Mask": "Edge",
    "Method": "EdgeRegressor",
    "Retained": true,
    "SingularValue": 119.7295676218,
    "VarianceExplained": 0.0087612574
  },
  "edge_comp_13": {
    "CumulativeVarianceExplained": 0.2290692271,
    "Mask": "Edge",
    "Method": "EdgeRegressor",
    "Retained": true,
    "SingularValue": 118.8255756434,
    "VarianceExplained": 0.0086294569
  },
  "edge_comp_14": {
    "CumulativeVarianceExplained": 0.2373717452,
    "Mask": "Edge",
    "Method": "EdgeRegressor",
    "Retained": true,
    "SingularValue": 116.552906972,
    "VarianceExplained": 0.0083025181
  },
  "edge_comp_15": {
    "CumulativeVarianceExplained": 0.2453908034,
    "Mask": "Edge",
    "Method": "EdgeRegressor",
    "Retained": true,
    "SingularValue": 114.5459866279,
    "VarianceExplained": 0.0080190582
  },
  "edge_comp_16": {
    "CumulativeVarianceExplained": 0.2531664665,
    "Mask": "Edge",
    "Method": "EdgeRegressor",
    "Retained": true,
    "SingularValue": 112.7942376157,
    "VarianceExplained": 0.0077756631
  },
  "edge_comp_17": {
    "CumulativeVarianceExplained": 0.2607770406,
    "Mask": "Edge",
    "Method": "EdgeRegressor",
    "Retained": true,
    "SingularValue": 111.5904173564,
    "VarianceExplained": 0.007610574
  },
  "edge_comp_18": {
    "CumulativeVarianceExplained": 0.268353893,
    "Mask": "Edge",
    "Method": "EdgeRegressor",
    "Retained": true,
    "SingularValue": 111.3429208225,
    "VarianceExplained": 0.0075768525
  },
  "edge_comp_19": {
    "CumulativeVarianceExplained": 0.2758306155,
    "Mask": "Edge",
    "Method": "EdgeRegressor",
    "Retained": true,
    "SingularValue": 110.6047616214,
    "VarianceExplained": 0.0074767225
  },
  "edge_comp_20": {
    "CumulativeVarianceExplained": 0.2832554035,
    "Mask": "Edge",
    "Method": "EdgeRegressor",
    "Retained": true,
    "SingularValue": 110.2199532367,
    "VarianceExplained": 0.007424788
  },
  "edge_comp_21": {
    "CumulativeVarianceExplained": 0.2905166091,
    "Mask": "Edge",
    "Method": "EdgeRegressor",
    "Retained": true,
    "SingularValue": 108.9990119178,
    "VarianceExplained": 0.0072612056
  },
  "edge_comp_22": {
    "CumulativeVarianceExplained": 0.2977443309,
    "Mask": "Edge",
    "Method": "EdgeRegressor",
    "Retained": true,
    "SingularValue": 108.7474068281,
    "VarianceExplained": 0.0072277219
  },
  "edge_comp_23": {
    "CumulativeVarianceExplained": 0.3049105173,
    "Mask": "Edge",
    "Method": "EdgeRegressor",
    "Retained": true,
    "SingularValue": 108.2834900185,
    "VarianceExplained": 0.0071661864
  },
  "t_comp_cor_00": {
    "CumulativeVarianceExplained": 0.2319749708,
    "Method": "tCompCor",
    "Retained": true,
    "SingularValue": 165.377897733,
    "VarianceExplained": 0.2319749708
  },
  "t_comp_cor_01": {
    "CumulativeVarianceExplained": 0.4163630331,
    "Method": "tCompCor",
    "Retained": true,
    "SingularValue": 147.4427093675,
    "VarianceExplained": 0.1843880623
  },
  "t_comp_cor_02": {
    "CumulativeVarianceExplained": 0.5027326841,
    "Method": "tCompCor",
    "Retained": true,
    "SingularValue": 100.9107618286,
    "VarianceExplained": 0.086369651
  },
  "w_comp_cor_00": {
    "CumulativeVarianceExplained": 0.023211718,
    "Mask": "WM",
    "Method": "aCompCor",
    "Retained": true,
    "SingularValue": 68.5846531293,
    "VarianceExplained": 0.023211718
  },
  "w_comp_cor_01": {
    "CumulativeVarianceExplained": 0.0402336762,
    "Mask": "WM",
    "Method": "aCompCor",
    "Retained": true,
    "SingularValue": 58.7324427145,
    "VarianceExplained": 0.0170219582
  },
  "w_comp_cor_02": {
    "CumulativeVarianceExplained": 0.0555531286,
    "Mask": "WM",
    "Method": "aCompCor",
    "Retained": true,
    "SingularValue": 55.7179238046,
    "VarianceExplained": 0.0153194524
  },
  "w_comp_cor_03": {
    "CumulativeVarianceExplained": 0.0688618504,
    "Mask": "WM",
    "Method": "aCompCor",
    "Retained": true,
    "SingularValue": 51.9327687716,
    "VarianceExplained": 0.0133087218
  },
  "w_comp_cor_04": {
    "CumulativeVarianceExplained": 0.0810338227,
    "Mask": "WM",
    "Method": "aCompCor",
    "Retained": true,
    "SingularValue": 49.6653823004,
    "VarianceExplained": 0.0121719724
  },
  "w_comp_cor_05": {
    "CumulativeVarianceExplained": 0.0928858367,
    "Mask": "WM",
    "Method": "aCompCor",
    "Retained": true,
    "SingularValue": 49.008271076,
    "VarianceExplained": 0.011852014
  },
  "w_comp_cor_06": {
    "CumulativeVarianceExplained": 0.1044334937,
    "Mask": "WM",
    "Method": "aCompCor",
    "Retained": true,
    "SingularValue": 48.3749179865,
    "VarianceExplained": 0.011547657
  },
  "w_comp_cor_07": {
    "CumulativeVarianceExplained": 0.1158132076,
    "Mask": "WM",
    "Method": "aCompCor",
    "Retained": true,
    "SingularValue": 48.0218598791,
    "VarianceExplained": 0.0113797139
  },
  "w_comp_cor_08": {
    "CumulativeVarianceExplained": 0.1270876096,
    "Mask": "WM",
    "Method": "aCompCor",
    "Retained": true,
    "SingularValue": 47.7991376448,
    "VarianceExplained": 0.011274402
  },
  "w_comp_cor_09": {
    "CumulativeVarianceExplained": 0.1383203043,
    "Mask": "WM",
    "Method": "aCompCor",
    "Retained": true,
    "SingularValue": 47.7106443921,
    "VarianceExplained": 0.0112326947
  },
  "w_comp_cor_10": {
    "CumulativeVarianceExplained": 0.1491945997,
    "Mask": "WM",
    "Method": "aCompCor",
    "Retained": true,
    "SingularValue": 46.943326975,
    "VarianceExplained": 0.0108742953
  },
  "w_comp_cor_11": {
    "CumulativeVarianceExplained": 0.1599978885,
    "Mask": "WM",
    "Method": "aCompCor",
    "Retained": true,
    "SingularValue": 46.7898117636,
    "VarianceExplained": 0.0108032888
  },
  "w_comp_cor_12": {
    "CumulativeVarianceExplained": 0.1705220647,
    "Mask": "WM",
    "Method": "aCompCor",
    "Retained": true,
    "SingularValue": 46.1814281077,
    "VarianceExplained": 0.0105241762
  },
  "w_comp_cor_13": {
    "CumulativeVarianceExplained": 0.1810128815,
    "Mask": "WM",
    "Method": "aCompCor",
    "Retained": true,
    "SingularValue": 46.1081775092,
    "VarianceExplained": 0.0104908168
  },
  "w_comp_cor_14": {
    "CumulativeVarianceExplained": 0.191422759,
    "Mask": "WM",
    "Method": "aCompCor",
    "Retained": true,
    "SingularValue": 45.9299647861,
    "VarianceExplained": 0.0104098775
  },
  "w_comp_cor_15": {
    "CumulativeVarianceExplained": 0.201736824,
    "Mask": "WM",
    "Method": "aCompCor",
    "Retained": true,
    "SingularValue": 45.7181067624,
    "VarianceExplained": 0.0103140651
  },
  "w_comp_cor_16": {
    "CumulativeVarianceExplained": 0.211893344,
    "Mask": "WM",
    "Method": "aCompCor",
    "Retained": true,
    "SingularValue": 45.3675960987,
    "VarianceExplained": 0.01015652
  },
  "w_comp_cor_17": {
    "CumulativeVarianceExplained": 0.2219184397,
    "Mask": "WM",
    "Method": "aCompCor",
    "Retained": true,
    "SingularValue": 45.0731142817,
    "VarianceExplained": 0.0100250956
  },
  "w_comp_cor_18": {
    "CumulativeVarianceExplained": 0.2318163604,
    "Mask": "WM",
    "Method": "aCompCor",
    "Retained": true,
    "SingularValue": 44.786310836,
    "VarianceExplained": 0.0098979207
  },
  "w_comp_cor_19": {
    "CumulativeVarianceExplained": 0.2416841793,
    "Mask": "WM",
    "Method": "aCompCor",
    "Retained": true,
    "SingularValue": 44.7181562874,
    "VarianceExplained": 0.0098678189
  },
  "w_comp_cor_20": {
    "CumulativeVarianceExplained": 0.2515232794,
    "Mask": "WM",
    "Method": "aCompCor",
    "Retained": true,
    "SingularValue": 44.6530361381,
    "VarianceExplained": 0.0098391001
  },
  "w_comp_cor_21": {
    "CumulativeVarianceExplained": 0.2612738721,
    "Mask": "WM",
    "Method": "aCompCor",
    "Retained": true,
    "SingularValue": 44.4517447361,
    "VarianceExplained": 0.0097505927
  },
  "w_comp_cor_22": {
    "CumulativeVarianceExplained": 0.2709657177,
    "Mask": "WM",
    "Method": "aCompCor",
    "Retained": true,
    "SingularValue": 44.3176320284,
    "VarianceExplained": 0.0096918456
  },
  "w_comp_cor_23": {
    "CumulativeVarianceExplained": 0.2806165204,
    "Mask": "WM",
    "Method": "aCompCor",
    "Retained": true,
    "SingularValue": 44.2236945113,
    "VarianceExplained": 0.0096508026
  },
  "w_comp_cor_24": {
    "CumulativeVarianceExplained": 0.2901405746,
    "Mask": "WM",
    "Method": "aCompCor",
    "Retained": true,
    "SingularValue": 43.9323296679,
    "VarianceExplained": 0.0095240542
  },
  "w_comp_cor_25": {
    "CumulativeVarianceExplained": 0.2995399154,
    "Mask": "WM",
    "Method": "aCompCor",
    "Retained": true,
    "SingularValue": 43.6437442657,
    "VarianceExplained": 0.0093993408
  },
  "w_comp_cor_26": {
    "CumulativeVarianceExplained": 0.3087713477,
    "Mask": "WM",
    "Method": "aCompCor",
    "Retained": true,
    "SingularValue": 43.2521647472,
    "VarianceExplained": 0.0092314323
  },
  "w_comp_cor_27": {
    "CumulativeVarianceExplained": 0.3179523062,
    "Mask": "WM",
    "Method": "aCompCor",
    "Retained": true,
    "SingularValue": 43.133759907,
    "VarianceExplained": 0.0091809585
  },
  "w_comp_cor_28": {
    "CumulativeVarianceExplained": 0.3270416308,
    "Mask": "WM",
    "Method": "aCompCor",
    "Retained": true,
    "SingularValue": 42.9179638981,
    "VarianceExplained": 0.0090893246
  },
  "w_comp_cor_29": {
    "CumulativeVarianceExplained": 0.3360466839,
    "Mask": "WM",
    "Method": "aCompCor",
    "Retained": true,
    "SingularValue": 42.7185440557,
    "VarianceExplained": 0.0090050531
  },
  "w_comp_cor_30": {
    "CumulativeVarianceExplained": 0.3449742194,
    "Mask": "WM",
    "Method": "aCompCor",
    "Retained": true,
    "SingularValue": 42.5342812366,
    "VarianceExplained": 0.0089275356
  },
  "w_comp_cor_31": {
    "CumulativeVarianceExplained": 0.3538412401,
    "Mask": "WM",
    "Method": "aCompCor",
    "Retained": true,
    "SingularValue": 42.3898778156,
    "VarianceExplained": 0.0088670207
  },
  "w_comp_cor_32": {
    "CumulativeVarianceExplained": 0.3626005982,
    "Mask": "WM",
    "Method": "aCompCor",
    "Retained": true,
    "SingularValue": 42.1317448564,
    "VarianceExplained": 0.0087593581
  },
  "w_comp_cor_33": {
    "CumulativeVarianceExplained": 0.3711978757,
    "Mask": "WM",
    "Method": "aCompCor",
    "Retained": true,
    "SingularValue": 41.7401278462,
    "VarianceExplained": 0.0085972774
  },
  "w_comp_cor_34": {
    "CumulativeVarianceExplained": 0.3797487334,
    "Mask": "WM",
    "Method": "aCompCor",
    "Retained": true,
    "SingularValue": 41.6272905933,
    "VarianceExplained": 0.0085508577
  },
  "w_comp_cor_35": {
    "CumulativeVarianceExplained": 0.3881878801,
    "Mask": "WM",
    "Method": "aCompCor",
    "Retained": true,
    "SingularValue": 41.3544806917,
    "VarianceExplained": 0.0084391467
  },
  "w_comp_cor_36": {
    "CumulativeVarianceExplained": 0.3965913415,
    "Mask": "WM",
    "Method": "aCompCor",
    "Retained": true,
    "SingularValue": 41.2669534428,
    "VarianceExplained": 0.0084034614
  },
  "w_comp_cor_37": {
    "CumulativeVarianceExplained": 0.4049194635,
    "Mask": "WM",
    "Method": "aCompCor",
    "Retained": true,
    "SingularValue": 41.0815520981,
    "VarianceExplained": 0.008328122
  },
  "w_comp_cor_38": {
    "CumulativeVarianceExplained": 0.4132409867,
    "Mask": "WM",
    "Method": "aCompCor",
    "Retained": true,
    "SingularValue": 41.0652735597,
    "VarianceExplained": 0.0083215233
  },
  "w_comp_cor_39": {
    "CumulativeVarianceExplained": 0.4214315981,
    "Mask": "WM",
    "Method": "aCompCor",
    "Retained": true,
    "SingularValue": 40.7409793273,
    "VarianceExplained": 0.0081906114
  },
  "w_comp_cor_40": {
    "CumulativeVarianceExplained": 0.4295932197,
    "Mask": "WM",
    "Method": "aCompCor",
    "Retained": true,
    "SingularValue": 40.6688162973,
    "VarianceExplained": 0.0081616216
  },
  "w_comp_cor_41": {
    "CumulativeVarianceExplained": 0.4376933797,
    "Mask": "WM",
    "Method": "aCompCor",
    "Retained": true,
    "SingularValue": 40.5153973114,
    "VarianceExplained": 0.00810016
  },
  "w_comp_cor_42": {
    "CumulativeVarianceExplained": 0.4456760073,
    "Mask": "WM",
    "Method": "aCompCor",
    "Retained": true,
    "SingularValue": 40.220386388,
    "VarianceExplained": 0.0079826276
  },
  "w_comp_cor_43": {
    "CumulativeVarianceExplained": 0.4536166222,
    "Mask": "WM",
    "Method": "aCompCor",
    "Retained": true,
    "SingularValue": 40.1144064862,
    "VarianceExplained": 0.0079406149
  },
  "w_comp_cor_44": {
    "CumulativeVarianceExplained": 0.4615273913,
    "Mask": "WM",
    "Method": "aCompCor",
    "Retained": true,
    "SingularValue": 40.0389479718,
    "VarianceExplained": 0.0079107691
  },
  "w_comp_cor_45": {
    "CumulativeVarianceExplained": 0.4693470966,
    "Mask": "WM",
    "Method": "aCompCor",
    "Retained": true,
    "SingularValue": 39.8078295499,
    "VarianceExplained": 0.0078197054
  },
  "w_comp_cor_46": {
    "CumulativeVarianceExplained": 0.4771049395,
    "Mask": "WM",
    "Method": "aCompCor",
    "Retained": true,
    "SingularValue": 39.6500549718,
    "VarianceExplained": 0.0077578429
  },
  "w_comp_cor_47": {
    "CumulativeVarianceExplained": 0.4848313813,
    "Mask": "WM",
    "Method": "aCompCor",
    "Retained": true,
    "SingularValue": 39.5697287426,
    "VarianceExplained": 0.0077264418
  },
  "w_comp_cor_48": {
    "CumulativeVarianceExplained": 0.4924686197,
    "Mask": "WM",
    "Method": "aCompCor",
    "Retained": true,
    "SingularValue": 39.3406449854,
    "VarianceExplained": 0.0076372383
  },
  "w_comp_cor_49": {
    "CumulativeVarianceExplained": 0.5000783798,
    "Mask": "WM",
    "Method": "aCompCor",
    "Retained": true,
    "SingularValue": 39.2698088957,
    "VarianceExplained": 0.0076097601
  }
}