{
  "a_comp_cor_00": {
    "CumulativeVarianceExplained": 0.040117414,
    "Mask": "combined",
    "Method": "aCompCor",
    "Retained": true,
    "SingularValue": 80.5791750442,
    "VarianceExplained": 0.040117414
  },
  "a_comp_cor_01": {
    "CumulativeVarianceExplained": 0.0744973923,
    "Mask": "combined",
    "Method": "aCompCor",
    "Retained": true,
    "SingularValue": 74.5949025899,
    "VarianceExplained": 0.0343799783
  },
  "a_comp_cor_02": {
    "CumulativeVarianceExplained": 0.1053555269,
    "Mask": "combined",
    "Method": "aCompCor",
    "Retained": true,
    "SingularValue": 70.6709918251,
    "VarianceExplained": 0.0308581346
  },
  "a_comp_cor_03": {
    "CumulativeVarianceExplained": 0.1337639288,
    "Mask": "combined",
    "Method": "aCompCor",
    "Retained": true,
    "SingularValue": 67.8078155676,
    "VarianceExplained": 0.0284084019
  },
  "a_comp_cor_04": {
    "CumulativeVarianceExplained": 0.1564017045,
    "Mask": "combined",
    "Method": "aCompCor",
    "Retained": true,
    "SingularValue": 60.530355933,
    "VarianceExplained": 0.0226377757
  },
  "a_comp_cor_05": {
    "CumulativeVarianceExplained": 0.1759588756,
    "Mask": "combined",
    "Method": "aCompCor",
    "Retained": true,
    "SingularValue": 56.2612491153,
    "VarianceExplained": 0.0195571712
  },
  "a_comp_cor_06": {
    "CumulativeVarianceExplained": 0.1931668722,
    "Mask": "combined",
    "Method": "aCompCor",
    "Retained": true,
    "SingularValue": 52.774181643,
    "VarianceExplained": 0.0172079966
  },
  "a_comp_cor_07": {
    "CumulativeVarianceExplained": 0.2081487615,
    "Mask": "combined",
    "Method": "aCompCor",
    "Retained": true,
    "SingularValue": 49.2424489727,
    "VarianceExplained": 0.0149818893
  },
  "a_comp_cor_08": {
    "CumulativeVarianceExplained": 0.2227826822,
    "Mask": "combined",
    "Method": "aCompCor",
    "Retained": true,
    "SingularValue": 48.6672381334,
    "VarianceExplained": 0.0146339207
  },
  "a_comp_cor_09": {
    "CumulativeVarianceExplained": 0.2361002493,
    "Mask": "combined",
    "Method": "aCompCor",
    "Retained": true,
    "SingularValue": 46.4268050794,
    "VarianceExplained": 0.0133175671
  },
  "a_comp_cor_10": {
    "CumulativeVarianceExplained": 0.2482742847,
    "Mask": "combined",
    "Method": "aCompCor",
    "Retained": true,
    "SingularValue": 44.3888232112,
    "VarianceExplained": 0.0121740354
  },
  "a_comp_cor_11": {
    "CumulativeVarianceExplained": 0.2600284486,
    "Mask": "combined",
    "Method": "aCompCor",
    "Retained": true,
    "SingularValue": 43.6166417138,
    "VarianceExplained": 0.0117541639
  },
  "a_comp_cor_12": {
    "CumulativeVarianceExplained": 0.2711593343,
    "Mask": "combined",
    "Method": "aCompCor",
    "Retained": true,
    "SingularValue": 42.4444795721,
    "VarianceExplained": 0.0111308857
  },
  "a_comp_cor_13": {
    "CumulativeVarianceExplained": 0.2821010591,
    "Mask": "combined",
    "Method": "aCompCor",
    "Retained": true,
    "SingularValue": 42.0822783756,
    "VarianceExplained": 0.0109417248
  },
  "a_comp_cor_14": {
    "CumulativeVarianceExplained": 0.2925858104,
    "Mask": "combined",
    "Method": "aCompCor",
    "Retained": true,
    "SingularValue": 41.1941380582,
    "VarianceExplained": 0.0104847514
  },
  "a_comp_cor_15": {
    "CumulativeVarianceExplained": 0.302836537,
    "Mask": "combined",
    "Method": "aCompCor",
    "Retained": true,
    "SingularValue": 40.7318069608,
    "VarianceExplained": 0.0102507266
  },
  "a_comp_cor_16": {
    "CumulativeVarianceExplained": 0.3128450406,
    "Mask": "combined",
    "Method": "aCompCor",
    "Retained": true,
    "SingularValue": 40.2476868649,
    "VarianceExplained": 0.0100085035
  },
  "a_comp_cor_17": {
    "CumulativeVarianceExplained": 0.3228035721,
    "Mask": "combined",
    "Method": "aCompCor",
    "Retained": true,
    "SingularValue": 40.1470837406,
    "VarianceExplained": 0.0099585316
  },
  "a_comp_cor_18": {
    "CumulativeVarianceExplained": 0.3326153636,
    "Mask": "combined",
    "Method": "aCompCor",
    "Retained": true,
    "SingularValue": 39.850200096,
    "VarianceExplained": 0.0098117915
  },
  "a_comp_cor_19": {
    "CumulativeVarianceExplained": 0.3423167546,
    "Mask": "combined",
    "Method": "aCompCor",
    "Retained": true,
    "SingularValue": 39.6253724145,
    "VarianceExplained": 0.009701391
  },
  "a_comp_cor_20": {
    "CumulativeVarianceExplained": 0.3518436328,
    "Mask": "combined",
    "Method": "aCompCor",
    "Retained": true,
    "SingularValue": 39.2673558786,
    "VarianceExplained": 0.0095268782
  },
  "a_comp_cor_21": {
    "CumulativeVarianceExplained": 0.3612901259,
    "Mask": "combined",
    "Method": "aCompCor",
    "Retained": true,
    "SingularValue": 39.1013415074,
    "VarianceExplained": 0.0094464931
  },
  "a_comp_cor_22": {
    "CumulativeVarianceExplained": 0.370505634,
    "Mask": "combined",
    "Method": "aCompCor",
    "Retained": true,
    "SingularValue": 38.6203312083,
    "VarianceExplained": 0.0092155081
  },
  "a_comp_cor_23": {
    "CumulativeVarianceExplained": 0.3796169664,
    "Mask": "combined",
    "Method": "aCompCor",
    "Retained": true,
    "SingularValue": 38.4014210841,
    "VarianceExplained": 0.0091113324
  },
  "a_comp_cor_24": {
    "CumulativeVarianceExplained": 0.3884716315,
    "Mask": "combined",
    "Method": "aCompCor",
    "Retained": true,
    "SingularValue": 37.8566712846,
    "VarianceExplained": 0.0088546652
  },
  "a_comp_cor_25": {
    "CumulativeVarianceExplained": 0.3972708378,
    "Mask": "combined",
    "Method": "aCompCor",
    "Retained": true,
    "SingularValue": 37.7379322336,
    "VarianceExplained": 0.0087992062
  },
  "a_comp_cor_26": {
    "CumulativeVarianceExplained": 0.4060084045,
    "Mask": "combined",
    "Method": "aCompCor",
    "Retained": true,
    "SingularValue": 37.6055204726,
    "VarianceExplained": 0.0087375667
  },
  "a_comp_cor_27": {
    "CumulativeVarianceExplained": 0.414687595,
    "Mask": "combined",
    "Method": "aCompCor",
    "Retained": true,
    "SingularValue": 37.4796877518,
    "VarianceExplained": 0.0086791906
  },
  "a_comp_cor_28": {
    "CumulativeVarianceExplained": 0.4231812224,
    "Mask": "combined",
    "Method": "aCompCor",
    "Retained": true,
    "SingularValue": 37.0768606057,
    "VarianceExplained": 0.0084936274
  },
  "a_comp_cor_29": {
    "CumulativeVarianceExplained": 0.4315847857,
    "Mask": "combined",
    "Method": "aCompCor",
    "Retained": true,
    "SingularValue": 36.8797602352,
    "VarianceExplained": 0.0084035633
  },
  "a_comp_cor_30": {
    "CumulativeVarianceExplained": 0.4398620338,
    "Mask": "combined",
    "Method": "aCompCor",
    "Retained": true,
    "SingularValue": 36.6015381829,
    "VarianceExplained": 0.0082772481
  },
  "a_comp_cor_31": {
    "CumulativeVarianceExplained": 0.4480363876,
    "Mask": "combined",
    "Method": "aCompCor",
    "Retained": true,
    "SingularValue": 36.3733304352,
    "VarianceExplained": 0.0081743538
  },
  "a_comp_cor_32": {
    "CumulativeVarianceExplained": 0.4561359426,
    "Mask": "combined",
    "Method": "aCompCor",
    "Retained": true,
    "SingularValue": 36.2065323048,
    "VarianceExplained": 0.008099555
  },
  "a_comp_cor_33": {
    "CumulativeVarianceExplained": 0.4641388283,
    "Mask": "combined",
    "Method": "aCompCor",
    "Retained": true,
    "SingularValue": 35.989818692,
    "VarianceExplained": 0.0080028857
  },
  "a_comp_cor_34": {
    "CumulativeVarianceExplained": 0.4720825562,
    "Mask": "combined",
    "Method": "aCompCor",
    "Retained": true,
    "SingularValue": 35.8565524336,
    "VarianceExplained": 0.0079437278
  },
  "a_comp_cor_35": {
    "CumulativeVarianceExplained": 0.4799803085,
    "Mask": "combined",
    "Method": "aCompCor",
    "Retained": true,
    "SingularValue": 35.7526394215,
    "VarianceExplained": 0.0078977524
  },
  "a_comp_cor_36": {
    "CumulativeVarianceExplained": 0.4877875839,
    "Mask": "combined",
    "Method": "aCompCor",
    "Retained": true,
    "SingularValue": 35.5472575146,
    "VarianceExplained": 0.0078072754
  },
  "a_comp_cor_37": {
    "CumulativeVarianceExplained": 0.4955187691,
    "Mask": "combined",
    "Method": "aCompCor",
    "Retained": true,
    "SingularValue": 35.3736104571,
    "VarianceExplained": 0.0077311852
  },
  "a_comp_cor_38": {
    "CumulativeVarianceExplained": 0.5031820263,
    "Mask": "combined",
    "Method": "aCompCor",
    "Retained": true,
    "SingularValue": 35.2178673391,
    "VarianceExplained": 0.0076632572
  },
  "c_comp_cor_00": {
    "CumulativeVarianceExplained": 0.1239505231,
    "Mask": "CSF",
    "Method": "aCompCor",
    "Retained": true,
    "SingularValue": 64.3905660557,
    "VarianceExplained": 0.1239505231
  },
  "c_comp_cor_01": {
    "CumulativeVarianceExplained": 0.2299165358,
    "Mask": "CSF",
    "Method": "aCompCor",
    "Retained": true,
    "SingularValue": 59.5362337191,
    "VarianceExplained": 0.1059660127
  },
  "c_comp_cor_02": {
    "CumulativeVarianceExplained": 0.2950456266,
    "Mask": "CSF",
    "Method": "aCompCor",
    "Retained": true,
    "SingularValue": 46.6751335087,
    "VarianceExplained": 0.0651290908
  },
  "c_comp_cor_03": {
    "CumulativeVarianceExplained": 0.3468642866,
    "Mask": "CSF",
    "Method": "aCompCor",
    "Retained": true,
    "SingularValue": 41.6333301223,
    "VarianceExplained": 0.05181866
  },
  "c_comp_cor_04": {
    "CumulativeVarianceExplained": 0.3934246939,
    "Mask": "CSF",
    "Method": "aCompCor",
    "Retained": true,
    "SingularValue": 39.4644855955,
    "VarianceExplained": 0.0465604073
  },
  "c_comp_cor_05": {
    "CumulativeVarianceExplained": 0.43045739,
    "Mask": "CSF",
    "Method": "aCompCor",
    "Retained": true,
    "SingularValue": 35.1957907053,
    "VarianceExplained": 0.0370326961
  },
  "c_comp_cor_06": {
    "CumulativeVarianceExplained": 0.4627873562,
    "Mask": "CSF",
    "Method": "aCompCor",
    "Retained": true,
    "SingularValue": 32.8852150689,
    "VarianceExplained": 0.0323299662
  },
  "c_comp_cor_07": {
    "CumulativeVarianceExplained": 0.4907040158,
    "Mask": "CSF",
    "Method": "aCompCor",
    "Retained": true,
    "SingularValue": 30.5583420003,
    "VarianceExplained": 0.0279166597
  },
  "c_comp_cor_08": {
    "CumulativeVarianceExplained": 0.5109284536,
    "Mask": "CSF",
    "Method": "aCompCor",
    "Retained": true,
    "SingularValue": 26.0097566654,
    "VarianceExplained": 0.0202244377
  },
  "dropped_0": {
    "CumulativeVarianceExplained": 0.3353893303,
    "Mask": "Edge",
    "Method": "EdgeRegressor",
    "Retained": false,
    "SingularValue": 111.5083044999,
    "VarianceExplained": 0.0075910268
  },
  "dropped_1": {
    "CumulativeVarianceExplained": 0.3428692167,
    "Mask": "Edge",
    "Method": "EdgeRegressor",
    "Retained": false,
    "SingularValue": 110.6889965864,
    "VarianceExplained": 0.0074798864
  },
  "dropped_10": {
    "CumulativeVarianceExplained": 0.406092296,
    "Mask": "Edge",
    "Method": "EdgeRegressor",
    "Retained": false,
    "SingularValue": 104.9494112833,
    "VarianceExplained": 0.0067242851
  },
  "dropped_100": {
    "CumulativeVarianceExplained": 0.9072457645,
    "Mask": "Edge",
    "Method": "EdgeRegressor",
    "Retained": false,
    "SingularValue": 87.9355709607,
    "VarianceExplained": 0.0047207965
  },
  "dropped_101": {
    "CumulativeVarianceExplained": 0.9119648916,
    "Mask": "Edge",
    "Method": "EdgeRegressor",
    "Retained": false,
    "SingularValue": 87.9200213405,
    "VarianceExplained": 0.0047191271
  },
  "dropped_102": {
    "CumulativeVarianceExplained": 0.9166496313,
    "Mask": "Edge",
    "Method": "EdgeRegressor",
    "Retained": false,
    "SingularValue": 87.5991072669,
    "VarianceExplained": 0.0046847397
  },
  "dropped_103": {
    "CumulativeVarianceExplained": 0.921313521,
    "Mask": "Edge",
    "Method": "EdgeRegressor",
    "Retained": false,
    "SingularValue": 87.4039547128,
    "VarianceExplained": 0.0046638897
  },
  "dropped_104": {
    "CumulativeVarianceExplained": 0.9259594805,
    "Mask": "Edge",
    "Method": "EdgeRegressor",
    "Retained": false,
    "SingularValue": 87.2357824964,
    "VarianceExplained": 0.0046459596
  },
  "dropped_105": {
    "CumulativeVarianceExplained": 0.9305973888,
    "Mask": "Edge",
    "Method": "EdgeRegressor",
    "Retained": false,
    "SingularValue": 87.1601616641,
    "VarianceExplained": 0.0046379083
  },
  "dropped_106": {
    "CumulativeVarianceExplained": 0.9352311221,
    "Mask": "Edge",
    "Method": "EdgeRegressor",
    "Retained": false,
    "SingularValue": 87.1209221852,
    "VarianceExplained": 0.0046337333
  },
  "dropped_107": {
    "CumulativeVarianceExplained": 0.9398333084,
    "Mask": "Edge",
    "Method": "EdgeRegressor",
    "Retained": false,
    "SingularValue": 86.8238513047,
    "VarianceExplained": 0.0046021863
  },
  "dropped_108": {
    "CumulativeVarianceExplained": 0.9443894752,
    "Mask": "Edge",
    "Method": "EdgeRegressor",
    "Retained": false,
    "SingularValue": 86.3886644451,
    "VarianceExplained": 0.0045561669
  },
  "dropped_109": {
    "CumulativeVarianceExplained": 0.9489435282,
    "Mask": "Edge",
    "Method": "EdgeRegressor",
    "Retained": false,
    "SingularValue": 86.3686215928,
    "VarianceExplained": 0.004554053
  },
  "dropped_11": {
    "CumulativeVarianceExplained": 0.4127744394,
    "Mask": "Edge",
    "Method": "EdgeRegressor",
    "Retained": false,
    "SingularValue": 104.6200309863,
    "VarianceExplained": 0.0066821434
  },
  "dropped_110": {
    "CumulativeVarianceExplained": 0.9534743387,
    "Mask": "Edge",
    "Method": "EdgeRegressor",
    "Retained": false,
    "SingularValue": 86.1479401778,
    "VarianceExplained": 0.0045308105
  },
  "dropped_111": {
    "CumulativeVarianceExplained": 0.9579962637,
    "Mask": "Edge",
    "Method": "EdgeRegressor",
    "Retained": false,
    "SingularValue": 86.0634249472,
    "VarianceExplained": 0.004521925
  },
  "dropped_112": {
    "CumulativeVarianceExplained": 0.9624986976,
    "Mask": "Edge",
    "Method": "EdgeRegressor",
    "Retained": false,
    "SingularValue": 85.8777428666,
    "VarianceExplained": 0.0045024339
  },
  "dropped_113": {
    "CumulativeVarianceExplained": 0.9669843245,
    "Mask": "Edge",
    "Method": "EdgeRegressor",
    "Retained": false,
    "SingularValue": 85.7173081936,
    "VarianceExplained": 0.0044856269
  },
  "dropped_114": {
    "CumulativeVarianceExplained": 0.9714620935,
    "Mask": "Edge",
    "Method": "EdgeRegressor",
    "Retained": false,
    "SingularValue": 85.6421950265,
    "VarianceExplained": 0.004477769
  },
  "dropped_115": {
    "CumulativeVarianceExplained": 0.9759094754,
    "Mask": "Edge",
    "Method": "EdgeRegressor",
    "Retained": false,
    "SingularValue": 85.3511074629,
    "VarianceExplained": 0.0044473819
  },
  "dropped_116": {
    "CumulativeVarianceExplained": 0.9803446379,
    "Mask": "Edge",
    "Method": "EdgeRegressor",
    "Retained": false,
    "SingularValue": 85.2337735753,
    "VarianceExplained": 0.0044351625
  },
  "dropped_117": {
    "CumulativeVarianceExplained": 0.9847087369,
    "Mask": "Edge",
    "Method": "EdgeRegressor",
    "Retained": false,
    "SingularValue": 84.5481763453,
    "VarianceExplained": 0.004364099
  },
  "dropped_118": {
    "CumulativeVarianceExplained": 0.9890401882,
    "Mask": "Edge",
    "Method": "EdgeRegressor",
    "Retained": false,
    "SingularValue": 84.2313318155,
    "VarianceExplained": 0.0043314513
  },
  "dropped_119": {
    "CumulativeVarianceExplained": 0.9933195493,
    "Mask": "Edge",
    "Method": "EdgeRegressor",
    "Retained": false,
    "SingularValue": 83.7233155964,
    "VarianceExplained": 0.0042793612
  },
  "dropped_12": {
    "CumulativeVarianceExplained": 0.4194174504,
    "Mask": "Edge",
    "Method": "EdgeRegressor",
    "Retained": false,
    "SingularValue": 104.3132401581,
    "VarianceExplained": 0.006643011
  },
  "dropped_120": {
    "CumulativeVarianceExplained": 0.9971399479,
    "Mask": "Edge",
    "Method": "EdgeRegressor",
    "Retained": false,
    "SingularValue": 79.1063388948,
    "VarianceExplained": 0.0038203986
  },
  "dropped_121": {
    "CumulativeVarianceExplained": 1.0,
    "Mask": "Edge",
    "Method": "EdgeRegressor",
    "Retained": false,
    "SingularValue": 68.4453454521,
    "VarianceExplained": 0.0028600521
  },
  "dropped_122": {
    "CumulativeVarianceExplained": 1.0,
    "Mask": "Edge",
    "Method": "EdgeRegressor",
    "Retained": false,
    "SingularValue": 0.0,
    "VarianceExplained": 0.0
  },
  "dropped_123": {
    "CumulativeVarianceExplained": 1.0,
    "Mask": "Edge",
    "Method": "EdgeRegressor",
    "Retained": false,
    "SingularValue": 0.0,
    "VarianceExplained": 0.0
  },
  "dropped_124": {
    "CumulativeVarianceExplained": 1.0,
    "Mask": "Edge",
    "Method": "EdgeRegressor",
    "Retained": false,
    "SingularValue": 0.0,
    "VarianceExplained": 0.0
  },
  "dropped_125": {
    "CumulativeVarianceExplained": 1.0,
    "Mask": "Edge",
    "Method": "EdgeRegressor",
    "Retained": false,
    "SingularValue": 0.0,
    "VarianceExplained": 0.0
  },
  "dropped_13": {
    "CumulativeVarianceExplained": 0.4259824564,
    "Mask": "Edge",
    "Method": "EdgeRegressor",
    "Retained": false,
    "SingularValue": 103.6989868282,
    "VarianceExplained": 0.006565006
  },
  "dropped_14": {
    "CumulativeVarianceExplained": 0.4324626515,
    "Mask": "Edge",
    "Method": "EdgeRegressor",
    "Retained": false,
    "SingularValue": 103.0269847625,
    "VarianceExplained": 0.0064801951
  },
  "dropped_15": {
    "CumulativeVarianceExplained": 0.4389403464,
    "Mask": "Edge",
    "Method": "EdgeRegressor",
    "Retained": false,
    "SingularValue": 103.0071073476,
    "VarianceExplained": 0.0064776948
  },
  "dropped_16": {
    "CumulativeVarianceExplained": 0.4453697295,
    "Mask": "Edge",
    "Method": "EdgeRegressor",
    "Retained": false,
    "SingularValue": 102.6222667486,
    "VarianceExplained": 0.0064293832
  },
  "dropped_17": {
    "CumulativeVarianceExplained": 0.4517821696,
    "Mask": "Edge",
    "Method": "EdgeRegressor",
    "Retained": false,
    "SingularValue": 102.4869593338,
    "VarianceExplained": 0.0064124401
  },
  "dropped_18": {
    "CumulativeVarianceExplained": 0.4581435334,
    "Mask": "Edge",
    "Method": "EdgeRegressor",
    "Retained": false,
    "SingularValue": 102.0779794031,
    "VarianceExplained": 0.0063613638
  },
  "dropped_19": {
    "CumulativeVarianceExplained": 0.4644738923,
    "Mask": "Edge",
    "Method": "EdgeRegressor",
    "Retained": false,
    "SingularValue": 101.8289147241,
    "VarianceExplained": 0.0063303589
  },
  "dropped_2": {
    "CumulativeVarianceExplained": 0.3502540052,
    "Mask": "Edge",
    "Method": "EdgeRegressor",
    "Retained": false,
    "SingularValue": 109.9831053354,
    "VarianceExplained": 0.0073847884
  },
  "dropped_20": {
    "CumulativeVarianceExplained": 0.4707645003,
    "Mask": "Edge",
    "Method": "EdgeRegressor",
    "Retained": false,
    "SingularValue": 101.5086988212,
    "VarianceExplained": 0.006290608
  },
  "dropped_21": {
    "CumulativeVarianceExplained": 0.4770461133,
    "Mask": "Edge",
    "Method": "EdgeRegressor",
    "Retained": false,
    "SingularValue": 101.4360987786,
    "VarianceExplained": 0.006281613
  },
  "dropped_22": {
    "CumulativeVarianceExplained": 0.4832861745,
    "Mask": "Edge",
    "Method": "EdgeRegressor",
    "Retained": false,
    "SingularValue": 101.100050197,
    "VarianceExplained": 0.0062400611
  },
  "dropped_23": {
    "CumulativeVarianceExplained": 0.4895113805,
    "Mask": "Edge",
    "Method": "EdgeRegressor",
    "Retained": false,
    "SingularValue": 100.9796389399,
    "VarianceExplained": 0.006225206
  },
  "dropped_24": {
    "CumulativeVarianceExplained": 0.4957123829,
    "Mask": "Edge",
    "Method": "EdgeRegressor",
    "Retained": false,
    "SingularValue": 100.7831432107,
    "VarianceExplained": 0.0062010024
  },
  "dropped_25": {
    "CumulativeVarianceExplained": 0.5018927946,
    "Mask": "Edge",
    "Method": "EdgeRegressor",
    "Retained": false,
    "SingularValue": 100.6156759149,
    "VarianceExplained": 0.0061804116
  },
  "dropped_26": {
    "CumulativeVarianceExplained": 0.5080333507,
    "Mask": "Edge",
    "Method": "EdgeRegressor",
    "Retained": false,
    "SingularValue": 100.2907318183,
    "VarianceExplained": 0.0061405561
  },
  "dropped_27": {
    "CumulativeVarianceExplained": 0.5141549564,
    "Mask": "Edge",
    "Method": "EdgeRegressor",
    "Retained": false,
    "SingularValue": 100.1358584464,
    "VarianceExplained": 0.0061216057
  },
  "dropped_28": {
    "CumulativeVarianceExplained": 0.520253123,
    "Mask": "Edge",
    "Method": "EdgeRegressor",
    "Retained": false,
    "SingularValue": 99.9439687156,
    "VarianceExplained": 0.0060981666
  },
  "dropped_29": {
    "CumulativeVarianceExplained": 0.5263351737,
    "Mask": "Edge",
    "Method": "EdgeRegressor",
    "Retained": false,
    "SingularValue": 99.8118185048,
    "VarianceExplained": 0.0060820507
  },
  "dropped_3": {
    "CumulativeVarianceExplained": 0.3575247589,
    "Mask": "Edge",
    "Method": "EdgeRegressor",
    "Retained": false,
    "SingularValue": 109.1306311021,
    "VarianceExplained": 0.0072707538
  },
  "dropped_30": {
    "CumulativeVarianceExplained": 0.5323893169,
    "Mask": "Edge",
    "Method": "EdgeRegressor",
    "Retained": false,
    "SingularValue": 99.5825613901,
    "VarianceExplained": 0.0060541432
  },
  "dropped_31": {
    "CumulativeVarianceExplained": 0.5384221491,
    "Mask": "Edge",
    "Method": "EdgeRegressor",
    "Retained": false,
    "SingularValue": 99.4071383863,
    "VarianceExplained": 0.0060328322
  },
  "dropped_32": {
    "CumulativeVarianceExplained": 0.5444404651,
    "Mask": "Edge",
    "Method": "EdgeRegressor",
    "Retained": false,
    "SingularValue": 99.2874695324,
    "VarianceExplained": 0.006018316
  },
  "dropped_33": {
    "CumulativeVarianceExplained": 0.550411163,
    "Mask": "Edge",
    "Method": "EdgeRegressor",
    "Retained": false,
    "SingularValue": 98.8938984675,
    "VarianceExplained": 0.0059706979
  },
  "dropped_34": {
    "CumulativeVarianceExplained": 0.5563199081,
    "Mask": "Edge",
    "Method": "EdgeRegressor",
    "Retained": false,
    "SingularValue": 98.3794925842,
    "VarianceExplained": 0.0059087452
  },
  "dropped_35": {
    "CumulativeVarianceExplained": 0.5622235629,
    "Mask": "Edge",
    "Method": "EdgeRegressor",
    "Retained": false,
    "SingularValue": 98.337106602,
    "VarianceExplained": 0.0059036548
  },
  "dropped_36": {
    "CumulativeVarianceExplained": 0.5681139287,
    "Mask": "Edge",
    "Method": "EdgeRegressor",
    "Retained": false,
    "SingularValue": 98.2263672423,
    "VarianceExplained": 0.0058903658
  },
  "dropped_37": {
    "CumulativeVarianceExplained": 0.5739803712,
    "Mask": "Edge",
    "Method": "EdgeRegressor",
    "Retained": false,
    "SingularValue": 98.0266939779,
    "VarianceExplained": 0.0058664424
  },
  "dropped_38": {
    "CumulativeVarianceExplained": 0.5798368451,
    "Mask": "Edge",
    "Method": "EdgeRegressor",
    "Retained": false,
    "SingularValue": 97.943373044,
    "VarianceExplained": 0.0058564739
  },
  "dropped_39": {
    "CumulativeVarianceExplained": 0.5856882183,
    "Mask": "Edge",
    "Method": "EdgeRegressor",
    "Retained": false,
    "SingularValue": 97.9007112927,
    "VarianceExplained": 0.0058513732
  },
  "dropped_4": {
    "CumulativeVarianceExplained": 0.364718598,
    "Mask": "Edge",
    "Method": "EdgeRegressor",
    "Retained": false,
    "SingularValue": 108.5518694742,
    "VarianceExplained": 0.0071938391
  },
  "dropped_40": {
    "CumulativeVarianceExplained": 0.5915310423,
    "Mask": "Edge",
    "Method": "EdgeRegressor",
    "Retained": false,
    "SingularValue": 97.8291660023,
    "VarianceExplained": 0.005842824
  },
  "dropped_41": {
    "CumulativeVarianceExplained": 0.597357058,
    "Mask": "Edge",
    "Method": "EdgeRegressor",
    "Retained": false,
    "SingularValue": 97.6883500381,
    "VarianceExplained": 0.0058260157
  },
  "dropped_42": {
    "CumulativeVarianceExplained": 0.6031517338,
    "Mask": "Edge",
    "Method": "EdgeRegressor",
    "Retained": false,
    "SingularValue": 97.4252476613,
    "VarianceExplained": 0.0057946758
  },
  "dropped_43": {
    "CumulativeVarianceExplained": 0.6089326457,
    "Mask": "Edge",
    "Method": "EdgeRegressor",
    "Retained": false,
    "SingularValue": 97.3094739375,
    "VarianceExplained": 0.0057809119
  },
  "dropped_44": {
    "CumulativeVarianceExplained": 0.6146874711,
    "Mask": "Edge",
    "Method": "EdgeRegressor",
    "Retained": false,
    "SingularValue": 97.0896698246,
    "VarianceExplained": 0.0057548254
  },
  "dropped_45": {
    "CumulativeVarianceExplained": 0.6204098759,
    "Mask": "Edge",
    "Method": "EdgeRegressor",
    "Retained": false,
    "SingularValue": 96.815799373,
    "VarianceExplained": 0.0057224048
  },
  "dropped_46": {
    "CumulativeVarianceExplained": 0.6261014809,
    "Mask": "Edge",
    "Method": "EdgeRegressor",
    "Retained": false,
    "SingularValue": 96.5549013717,
    "VarianceExplained": 0.005691605
  },
  "dropped_47": {
    "CumulativeVarianceExplained": 0.6317664873,
    "Mask": "Edge",
    "Method": "EdgeRegressor",
    "Retained": false,
    "SingularValue": 96.3290228044,
    "VarianceExplained": 0.0056650065
  },
  "dropped_48": {
    "CumulativeVarianceExplained": 0.6374123437,
    "Mask": "Edge",
    "Method": "EdgeRegressor",
    "Retained": false,
    "SingularValue": 96.1660687061,
    "VarianceExplained": 0.0056458564
  },
  "dropped_49": {
    "CumulativeVarianceExplained": 0.6430478936,
    "Mask": "Edge",
    "Method": "EdgeRegressor",
    "Retained": false,
    "SingularValue": 96.078253084,
    "VarianceExplained": 0.0056355499
  },
  "dropped_5": {
    "CumulativeVarianceExplained": 0.3718551897,
    "Mask": "Edge",
    "Method": "EdgeRegressor",
    "Retained": false,
    "SingularValue": 108.1190882971,
    "VarianceExplained": 0.0071365917
  },
  "dropped_50": {
    "CumulativeVarianceExplained": 0.6486637008,
    "Mask": "Edge",
    "Method": "EdgeRegressor",
    "Retained": false,
    "SingularValue": 95.9098124262,
    "VarianceExplained": 0.0056158072
  },
  "dropped_51": {
    "CumulativeVarianceExplained": 0.6542677333,
    "Mask": "Edge",
    "Method": "EdgeRegressor",
    "Retained": false,
    "SingularValue": 95.8092132104,
    "VarianceExplained": 0.0056040326
  },
  "dropped_52": {
    "CumulativeVarianceExplained": 0.6598405422,
    "Mask": "Edge",
    "Method": "EdgeRegressor",
    "Retained": false,
    "SingularValue": 95.5419322822,
    "VarianceExplained": 0.0055728088
  },
  "dropped_53": {
    "CumulativeVarianceExplained": 0.6654008753,
    "Mask": "Edge",
    "Method": "EdgeRegressor",
    "Retained": false,
    "SingularValue": 95.4349293072,
    "VarianceExplained": 0.0055603332
  },
  "dropped_54": {
    "CumulativeVarianceExplained": 0.6709330804,
    "Mask": "Edge",
    "Method": "EdgeRegressor",
    "Retained": false,
    "SingularValue": 95.1932344508,
    "VarianceExplained": 0.0055322051
  },
  "dropped_55": {
    "CumulativeVarianceExplained": 0.6764568424,
    "Mask": "Edge",
    "Method": "EdgeRegressor",
    "Retained": false,
    "SingularValue": 95.1205663528,
    "VarianceExplained": 0.005523762
  },
  "dropped_56": {
    "CumulativeVarianceExplained": 0.6819772096,
    "Mask": "Edge",
    "Method": "EdgeRegressor",
    "Retained": false,
    "SingularValue": 95.0913327504,
    "VarianceExplained": 0.0055203673
  },
  "dropped_57": {
    "CumulativeVarianceExplained": 0.687485843,
    "Mask": "Edge",
    "Method": "EdgeRegressor",
    "Retained": false,
    "SingularValue": 94.9902173067,
    "VarianceExplained": 0.0055086333
  },
  "dropped_58": {
    "CumulativeVarianceExplained": 0.6929578601,
    "Mask": "Edge",
    "Method": "EdgeRegressor",
    "Retained": false,
    "SingularValue": 94.6739888101,
    "VarianceExplained": 0.0054720172
  },
  "dropped_59": {
    "CumulativeVarianceExplained": 0.6984194514,
    "Mask": "Edge",
    "Method": "EdgeRegressor",
    "Retained": false,
    "SingularValue": 94.5837536995,
    "VarianceExplained": 0.0054615912
  },
  "dropped_6": {
    "CumulativeVarianceExplained": 0.3788283071,
    "Mask": "Edge",
    "Method": "EdgeRegressor",
    "Retained": false,
    "SingularValue": 106.873599248,
    "VarianceExplained": 0.0069731173
  },
  "dropped_60": {
    "CumulativeVarianceExplained": 0.7038745733,
    "Mask": "Edge",
    "Method": "EdgeRegressor",
    "Retained": false,
    "SingularValue": 94.5277194328,
    "VarianceExplained": 0.0054551219
  },
  "dropped_61": {
    "CumulativeVarianceExplained": 0.7093233173,
    "Mask": "Edge",
    "Method": "EdgeRegressor",
    "Retained": false,
    "SingularValue": 94.472444152,
    "VarianceExplained": 0.005448744
  },
  "dropped_62": {
    "CumulativeVarianceExplained": 0.7147444806,
    "Mask": "Edge",
    "Method": "EdgeRegressor",
    "Retained": false,
    "SingularValue": 94.2330375743,
    "VarianceExplained": 0.0054211632
  },
  "dropped_63": {
    "CumulativeVarianceExplained": 0.7201523232,
    "Mask": "Edge",
    "Method": "EdgeRegressor",
    "Retained": false,
    "SingularValue": 94.1171938918,
    "VarianceExplained": 0.0054078426
  },
  "dropped_64": {
    "CumulativeVarianceExplained": 0.7255503682,
    "Mask": "Edge",
    "Method": "EdgeRegressor",
    "Retained": false,
    "SingularValue": 94.0318972125,
    "VarianceExplained": 0.005398045
  },
  "dropped_65": {
    "CumulativeVarianceExplained": 0.730918879,
    "Mask": "Edge",
    "Method": "EdgeRegressor",
    "Retained": false,
    "SingularValue": 93.7743071293,
    "VarianceExplained": 0.0053685108
  },
  "dropped_66": {
    "CumulativeVarianceExplained": 0.7362498778,
    "Mask": "Edge",
    "Method": "EdgeRegressor",
    "Retained": false,
    "SingularValue": 93.4461130713,
    "VarianceExplained": 0.0053309988
  },
  "dropped_67": {
    "CumulativeVarianceExplained": 0.7415779129,
    "Mask": "Edge",
    "Method": "EdgeRegressor",
    "Retained": false,
    "SingularValue": 93.4201341537,
    "VarianceExplained": 0.0053280351
  },
  "dropped_68": {
    "CumulativeVarianceExplained": 0.7468793595,
    "Mask": "Edge",
    "Method": "EdgeRegressor",
    "Retained": false,
    "SingularValue": 93.1867461746,
    "VarianceExplained": 0.0053014467
  },
  "dropped_69": {
    "CumulativeVarianceExplained": 0.7521571592,
    "Mask": "Edge",
    "Method": "EdgeRegressor",
    "Retained": false,
    "SingularValue": 92.9786844905,
    "VarianceExplained": 0.0052777996
  },
  "dropped_7": {
    "CumulativeVarianceExplained": 0.3857875295,
    "Mask": "Edge",
    "Method": "EdgeRegressor",
    "Retained": false,
    "SingularValue": 106.7670661194,
    "VarianceExplained": 0.0069592225
  },
  "dropped_70": {
    "CumulativeVarianceExplained": 0.7574231882,
    "Mask": "Edge",
    "Method": "EdgeRegressor",
    "Retained": false,
    "SingularValue": 92.8749458378,
    "VarianceExplained": 0.005266029
  },
  "dropped_71": {
    "CumulativeVarianceExplained": 0.7626513238,
    "Mask": "Edge",
    "Method": "EdgeRegressor",
    "Retained": false,
    "SingularValue": 92.5401866742,
    "VarianceExplained": 0.0052281356
  },
  "dropped_72": {
    "CumulativeVarianceExplained": 0.7678728295,
    "Mask": "Edge",
    "Method": "EdgeRegressor",
    "Retained": false,
    "SingularValue": 92.4814914725,
    "VarianceExplained": 0.0052215057
  },
  "dropped_73": {
    "CumulativeVarianceExplained": 0.7730846964,
    "Mask": "Edge",
    "Method": "EdgeRegressor",
    "Retained": false,
    "SingularValue": 92.3960929356,
    "VarianceExplained": 0.0052118669
  },
  "dropped_74": {
    "CumulativeVarianceExplained": 0.7782842125,
    "Mask": "Edge",
    "Method": "EdgeRegressor",
    "Retained": false,
    "SingularValue": 92.2865503392,
    "VarianceExplained": 0.0051995161
  },
  "dropped_75": {
    "CumulativeVarianceExplained": 0.7834713751,
    "Mask": "Edge",
    "Method": "EdgeRegressor",
    "Retained": false,
    "SingularValue": 92.1768534581,
    "VarianceExplained": 0.0051871626
  },
  "dropped_76": {
    "CumulativeVarianceExplained": 0.7886226872,
    "Mask": "Edge",
    "Method": "EdgeRegressor",
    "Retained": false,
    "SingularValue": 91.8577662007,
    "VarianceExplained": 0.0051513121
  },
  "dropped_77": {
    "CumulativeVarianceExplained": 0.7937682798,
    "Mask": "Edge",
    "Method": "EdgeRegressor",
    "Retained": false,
    "SingularValue": 91.806757643,
    "VarianceExplained": 0.0051455926
  },
  "dropped_78": {
    "CumulativeVarianceExplained": 0.7989028573,
    "Mask": "Edge",
    "Method": "EdgeRegressor",
    "Retained": false,
    "SingularValue": 91.7084402921,
    "VarianceExplained": 0.0051345775
  },
  "dropped_79": {
    "CumulativeVarianceExplained": 0.8040206756,
    "Mask": "Edge",
    "Method": "EdgeRegressor",
    "Retained": false,
    "SingularValue": 91.5586497305,
    "VarianceExplained": 0.0051178183
  },
  "dropped_8": {
    "CumulativeVarianceExplained": 0.3925955267,
    "Mask": "Edge",
    "Method": "EdgeRegressor",
    "Retained": false,
    "SingularValue": 105.600660206,
    "VarianceExplained": 0.0068079972
  },
  "dropped_80": {
    "CumulativeVarianceExplained": 0.8091149043,
    "Mask": "Edge",
    "Method": "EdgeRegressor",
    "Retained": false,
    "SingularValue": 91.3473952847,
    "VarianceExplained": 0.0050942287
  },
  "dropped_81": {
    "CumulativeVarianceExplained": 0.8142037097,
    "Mask": "Edge",
    "Method": "EdgeRegressor",
    "Retained": false,
    "SingularValue": 91.2987577602,
    "VarianceExplained": 0.0050888054
  },
  "dropped_82": {
    "CumulativeVarianceExplained": 0.8192612064,
    "Mask": "Edge",
    "Method": "EdgeRegressor",
    "Retained": false,
    "SingularValue": 91.0174689718,
    "VarianceExplained": 0.0050574967
  },
  "dropped_83": {
    "CumulativeVarianceExplained": 0.8243016431,
    "Mask": "Edge",
    "Method": "EdgeRegressor",
    "Retained": false,
    "SingularValue": 90.8638281706,
    "VarianceExplained": 0.0050404367
  },
  "dropped_84": {
    "CumulativeVarianceExplained": 0.8293387191,
    "Mask": "Edge",
    "Method": "EdgeRegressor",
    "Retained": false,
    "SingularValue": 90.8335313368,
    "VarianceExplained": 0.005037076
  },
  "dropped_85": {
    "CumulativeVarianceExplained": 0.8343525742,
    "Mask": "Edge",
    "Method": "EdgeRegressor",
    "Retained": false,
    "SingularValue": 90.6239196602,
    "VarianceExplained": 0.0050138552
  },
  "dropped_86": {
    "CumulativeVarianceExplained": 0.8393556087,
    "Mask": "Edge",
    "Method": "EdgeRegressor",
    "Retained": false,
    "SingularValue": 90.5260758509,
    "VarianceExplained": 0.0050030344
  },
  "dropped_87": {
    "CumulativeVarianceExplained": 0.8443191929,
    "Mask": "Edge",
    "Method": "EdgeRegressor",
    "Retained": false,
    "SingularValue": 90.1684588152,
    "VarianceExplained": 0.0049635842
  },
  "dropped_88": {
    "CumulativeVarianceExplained": 0.8492739699,
    "Mask": "Edge",
    "Method": "EdgeRegressor",
    "Retained": false,
    "SingularValue": 90.0884275079,
    "VarianceExplained": 0.004954777
  },
  "dropped_89": {
    "CumulativeVarianceExplained": 0.8542229851,
    "Mask": "Edge",
    "Method": "EdgeRegressor",
    "Retained": false,
    "SingularValue": 90.0360311163,
    "VarianceExplained": 0.0049490152
  },
  "dropped_9": {
    "CumulativeVarianceExplained": 0.3993680109,
    "Mask": "Edge",
    "Method": "EdgeRegressor",
    "Retained": false,
    "SingularValue": 105.32487382,
    "VarianceExplained": 0.0067724842
  },
  "dropped_90": {
    "CumulativeVarianceExplained": 0.8591480482,
    "Mask": "Edge",
    "Method": "EdgeRegressor",
    "Retained": false,
    "SingularValue": 89.8178892627,
    "VarianceExplained": 0.004925063
  },
  "dropped_91": {
    "CumulativeVarianceExplained": 0.8640672331,
    "Mask": "Edge",
    "Method": "EdgeRegressor",
    "Retained": false,
    "SingularValue": 89.7642746472,
    "VarianceExplained": 0.004919185
  },
  "dropped_92": {
    "CumulativeVarianceExplained": 0.8689313612,
    "Mask": "Edge",
    "Method": "EdgeRegressor",
    "Retained": false,
    "SingularValue": 89.260527297,
    "VarianceExplained": 0.004864128
  },
  "dropped_93": {
    "CumulativeVarianceExplained": 0.8737889519,
    "Mask": "Edge",
    "Method": "EdgeRegressor",
    "Retained": false,
    "SingularValue": 89.2005249874,
    "VarianceExplained": 0.0048575908
  },
  "dropped_94": {
    "CumulativeVarianceExplained": 0.8786326082,
    "Mask": "Edge",
    "Method": "EdgeRegressor",
    "Retained": false,
    "SingularValue": 89.0724928457,
    "VarianceExplained": 0.0048436563
  },
  "dropped_95": {
    "CumulativeVarianceExplained": 0.8834441958,
    "Mask": "Edge",
    "Method": "EdgeRegressor",
    "Retained": false,
    "SingularValue": 88.7771392722,
    "VarianceExplained": 0.0048115876
  },
  "dropped_96": {
    "CumulativeVarianceExplained": 0.8882425428,
    "Mask": "Edge",
    "Method": "EdgeRegressor",
    "Retained": false,
    "SingularValue": 88.6549065411,
    "VarianceExplained": 0.004798347
  },
  "dropped_97": {
    "CumulativeVarianceExplained": 0.8930312201,
    "Mask": "Edge",
    "Method": "EdgeRegressor",
    "Retained": false,
    "SingularValue": 88.5655315271,
    "VarianceExplained": 0.0047886773
  },
  "dropped_98": {
    "CumulativeVarianceExplained": 0.8977814025,
    "Mask": "Edge",
    "Method": "EdgeRegressor",
    "Retained": false,
    "SingularValue": 88.2088362956,
    "VarianceExplained": 0.0047501824
  },
  "dropped_99": {
    "CumulativeVarianceExplained": 0.902524968,
    "Mask": "Edge",
    "Method": "EdgeRegressor",
    "Retained": false,
    "SingularValue": 88.1473782749,
    "VarianceExplained": 0.0047435655
  },
  "edge_comp_00": {
    "CumulativeVarianceExplained": 0.0313255494,
    "Mask": "Edge",
    "Method": "EdgeRegressor",
    "Retained": true,
    "SingularValue": 226.5198663894,
    "VarianceExplained": 0.0313255494
  },
  "edge_comp_01": {
    "CumulativeVarianceExplained": 0.0600832819,
    "Mask": "Edge",
    "Method": "EdgeRegressor",
    "Retained": true,
    "SingularValue": 217.037245454,
    "VarianceExplained": 0.0287577325
  },
  "edge_comp_02": {
    "CumulativeVarianceExplained": 0.0830385941,
    "Mask": "Edge",
    "Method": "EdgeRegressor",
    "Retained": true,
    "SingularValue": 193.9092604307,
    "VarianceExplained": 0.0229553121
  },
  "edge_comp_03": {
    "CumulativeVarianceExplained": 0.105223563,
    "Mask": "Edge",
    "Method": "EdgeRegressor",
    "Retained": true,
    "SingularValue": 190.6278549903,
    "VarianceExplained": 0.0221849689
  },
  "edge_comp_04": {
    "CumulativeVarianceExplained": 0.1247099466,
    "Mask": "Edge",
    "Method": "EdgeRegressor",
    "Retained": true,
    "SingularValue": 178.6580431625,
    "VarianceExplained": 0.0194863836
  },
  "edge_comp_05": {
    "CumulativeVarianceExplained": 0.1432152188,
    "Mask": "Edge",
    "Method": "EdgeRegressor",
    "Retained": true,
    "SingularValue": 174.1023717608,
    "VarianceExplained": 0.0185052722
  },
  "edge_comp_06": {
    "CumulativeVarianceExplained": 0.1578996807,
    "Mask": "Edge",
    "Method": "EdgeRegressor",
    "Retained": true,
    "SingularValue": 155.09077529,
    "VarianceExplained": 0.0146844619
  },
  "edge_comp_07": {
    "CumulativeVarianceExplained": 0.1720792661,
    "Mask": "Edge",
    "Method": "EdgeRegressor",
    "Retained": true,
    "SingularValue": 152.4013150761,
    "VarianceExplained": 0.0141795854
  },
  "edge_comp_08": {
    "CumulativeVarianceExplained": 0.1851511036,
    "Mask": "Edge",
    "Method": "EdgeRegressor",
    "Retained": true,
    "SingularValue": 146.3272698607,
    "VarianceExplained": 0.0130718375
  },
  "edge_comp_09": {
    "CumulativeVarianceExplained": 0.1975055979,
    "Mask": "Edge",
    "Method": "EdgeRegressor",
    "Retained": true,
    "SingularValue": 142.2556206907,
    "VarianceExplained": 0.0123544943
  },
  "edge_comp_10": {
    "CumulativeVarianceExplained": 0.2090850013,
    "Mask": "Edge",
    "Method": "EdgeRegressor",
    "Retained": true,
    "SingularValue": 137.7209597622,
    "VarianceExplained": 0.0115794034
  },
  "edge_comp_11": {
    "CumulativeVarianceExplained": 0.2202931252,
    "Mask": "Edge",
    "Method": "EdgeRegressor",
    "Retained": true,
    "SingularValue": 135.4950441491,
    "VarianceExplained": 0.0112081239
  },
  "edge_comp_12": {
    "CumulativeVarianceExplained": 0.2310594574,
    "Mask": "Edge",
    "Method": "EdgeRegressor",
    "Retained": true,
    "SingularValue": 132.7977868669,
    "VarianceExplained": 0.0107663322
  },
  "edge_comp_13": {
    "CumulativeVarianceExplained": 0.2415327389,
    "Mask": "Edge",
    "Method": "EdgeRegressor",
    "Retained": true,
    "SingularValue": 130.9779945012,
    "VarianceExplained": 0.0104732815
  },
  "edge_comp_14": {
    "CumulativeVarianceExplained": 0.2514523496,
    "Mask": "Edge",
    "Method": "EdgeRegressor",
    "Retained": true,
    "SingularValue": 127.4689073657,
    "VarianceExplained": 0.0099196107
  },
  "edge_comp_15": {
    "CumulativeVarianceExplained": 0.2608103418,
    "Mask": "Edge",
    "Method": "EdgeRegressor",
    "Retained": true,
    "SingularValue": 123.807880009,
    "VarianceExplained": 0.0093579922
  },
  "edge_comp_16": {
    "CumulativeVarianceExplained": 0.2700495049,
    "Mask": "Edge",
    "Method": "EdgeRegressor",
    "Retained": true,
    "SingularValue": 123.0193042716,
    "VarianceExplained": 0.0092391631
  },
  "edge_comp_17": {
    "CumulativeVarianceExplained": 0.2790523631,
    "Mask": "Edge",
    "Method": "EdgeRegressor",
    "Retained": true,
    "SingularValue": 121.435916192,
    "VarianceExplained": 0.0090028582
  },
  "edge_comp_18": {
    "CumulativeVarianceExplained": 0.2875767288,
    "Mask": "Edge",
    "Method": "EdgeRegressor",
    "Retained": true,
    "SingularValue": 118.1647621171,
    "VarianceExplained": 0.0085243657
  },
  "edge_comp_19": {
    "CumulativeVarianceExplained": 0.2959204388,
    "Mask": "Edge",
    "Method": "EdgeRegressor",
    "Retained": true,
    "SingularValue": 116.9059318691,
    "VarianceExplained": 0.00834371
  },
  "edge_comp_20": {
    "CumulativeVarianceExplained": 0.3040672879,
    "Mask": "Edge",
    "Method": "EdgeRegressor",
    "Retained": true,
    "SingularValue": 115.5185647539,
    "VarianceExplained": 0.0081468491
  },
  "edge_comp_21": {
    "CumulativeVarianceExplained": 0.3121137055,
    "Mask": "Edge",
    "Method": "EdgeRegressor",
    "Retained": true,
    "SingularValue": 114.8043208778,
    "VarianceExplained": 0.0080464176
  },
  "edge_comp_22": {
    "CumulativeVarianceExplained": 0.3199861813,
    "Mask": "Edge",
    "Method": "EdgeRegressor",
    "Retained": true,
    "SingularValue": 113.5566616959,
    "VarianceExplained": 0.0078724758
  },
  "edge_comp_23": {
    "CumulativeVarianceExplained": 0.3277983035,
    "Mask": "Edge",
    "Method": "EdgeRegressor",
    "Retained": true,
    "SingularValue": 113.1205378351,
    "VarianceExplained": 0.0078121221
  },
  "t_comp_cor_00": {
    "CumulativeVarianceExplained": 0.1670679096,
    "Method": "tCompCor",
    "Retained": true,
    "SingularValue": 138.6404089586,
    "VarianceExplained": 0.1670679096
  },
  "t_comp_cor_01": {
    "CumulativeVarianceExplained": 0.3046462886,
    "Method": "tCompCor",
    "Retained": true,
    "SingularValue": 125.810939525,
    "VarianceExplained": 0.137578379
  },
  "t_comp_cor_02": {
    "CumulativeVarianceExplained": 0.4198657378,
    "Method": "tCompCor",
    "Retained": true,
    "SingularValue": 115.1346934302,
    "VarianceExplained": 0.1152194492
  },
  "t_comp_cor_03": {
    "CumulativeVarianceExplained": 0.4743786865,
    "Method": "tCompCor",
    "Retained": true,
    "SingularValue": 79.1941585262,
    "VarianceExplained": 0.0545129487
  },
  "t_comp_cor_04": {
    "CumulativeVarianceExplained": 0.5195306785,
    "Method": "tCompCor",
    "Retained": true,
    "SingularValue": 72.0745217261,
    "VarianceExplained": 0.045151992
  },
  "w_comp_cor_00": {
    "CumulativeVarianceExplained": 0.0427538384,
    "Mask": "WM",
    "Method": "aCompCor",
    "Retained": true,
    "SingularValue": 68.9353983306,
    "VarianceExplained": 0.0427538384
  },
  "w_comp_cor_01": {
    "CumulativeVarianceExplained": 0.0700226787,
    "Mask": "WM",
    "Method": "aCompCor",
    "Retained": true,
    "SingularValue": 55.0538971879,
    "VarianceExplained": 0.0272688403
  },
  "w_comp_cor_02": {
    "CumulativeVarianceExplained": 0.0903763756,
    "Mask": "WM",
    "Method": "aCompCor",
    "Retained": true,
    "SingularValue": 47.5637825457,
    "VarianceExplained": 0.0203536969
  },
  "w_comp_cor_03": {
    "CumulativeVarianceExplained": 0.1092020641,
    "Mask": "WM",
    "Method": "aCompCor",
    "Retained": true,
    "SingularValue": 45.743581762,
    "VarianceExplained": 0.0188256885
  },
  "w_comp_cor_04": {
    "CumulativeVarianceExplained": 0.1263085455,
    "Mask": "WM",
    "Method": "aCompCor",
    "Retained": true,
    "SingularValue": 43.604878293,
    "VarianceExplained": 0.0171064814
  },
  "w_comp_cor_05": {
    "CumulativeVarianceExplained": 0.1410647004,
    "Mask": "WM",
    "Method": "aCompCor",
    "Retained": true,
    "SingularValue": 40.4987236296,
    "VarianceExplained": 0.0147561549
  },
  "w_comp_cor_06": {
    "CumulativeVarianceExplained": 0.1553579038,
    "Mask": "WM",
    "Method": "aCompCor",
    "Retained": true,
    "SingularValue": 39.8583687706,
    "VarianceExplained": 0.0142932034
  },
  "w_comp_cor_07": {
    "CumulativeVarianceExplained": 0.1685703543,
    "Mask": "WM",
    "Method": "aCompCor",
    "Retained": true,
    "SingularValue": 38.3218458665,
    "VarianceExplained": 0.0132124505
  },
  "w_comp_cor_08": {
    "CumulativeVarianceExplained": 0.1816898054,
    "Mask": "WM",
    "Method": "aCompCor",
    "Retained": true,
    "SingularValue": 38.1867384799,
    "VarianceExplained": 0.0131194512
  },
  "w_comp_cor_09": {
    "CumulativeVarianceExplained": 0.1945842779,
    "Mask": "WM",
    "Method": "aCompCor",
    "Retained": true,
    "SingularValue": 37.8579002376,
    "VarianceExplained": 0.0128944724
  },
  "w_comp_cor_10": {
    "CumulativeVarianceExplained": 0.207118431,
    "Mask": "WM",
    "Method": "aCompCor",
    "Retained": true,
    "SingularValue": 37.3252075096,
    "VarianceExplained": 0.0125341531
  },
  "w_comp_cor_11": {
    "CumulativeVarianceExplained": 0.2191731412,
    "Mask": "WM",
    "Method": "aCompCor",
    "Retained": true,
    "SingularValue": 36.6043855501,
    "VarianceExplained": 0.0120547102
  },
  "w_comp_cor_12": {
    "CumulativeVarianceExplained": 0.2311083736,
    "Mask": "WM",
    "Method": "aCompCor",
    "Retained": true,
    "SingularValue": 36.4225353526,
    "VarianceExplained": 0.0119352324
  },
  "w_comp_cor_13": {
    "CumulativeVarianceExplained": 0.242933473,
    "Mask": "WM",
    "Method": "aCompCor",
    "Retained": true,
    "SingularValue": 36.2541004102,
    "VarianceExplained": 0.0118250994
  },
  "w_comp_cor_14": {
    "CumulativeVarianceExplained": 0.25428491,
    "Mask": "WM",
    "Method": "aCompCor",
    "Retained": true,
    "SingularValue": 35.5205887928,
    "VarianceExplained": 0.0113514371
  },
  "w_comp_cor_15": {
    "CumulativeVarianceExplained": 0.2655941245,
    "Mask": "WM",
    "Method": "aCompCor",
    "Retained": true,
    "SingularValue": 35.4544664569,
    "VarianceExplained": 0.0113092145
  },
  "w_comp_cor_16": {
    "CumulativeVarianceExplained": 0.276665491,
    "Mask": "WM",
    "Method": "aCompCor",
    "Retained": true,
    "SingularValue": 35.079657668,
    "VarianceExplained": 0.0110713665
  },
  "w_comp_cor_17": {
    "CumulativeVarianceExplained": 0.2874949892,
    "Mask": "WM",
    "Method": "aCompCor",
    "Retained": true,
    "SingularValue": 34.6943615261,
    "VarianceExplained": 0.0108294982
  },
  "w_comp_cor_18": {
    "CumulativeVarianceExplained": 0.2981959427,
    "Mask": "WM",
    "Method": "aCompCor",
    "Retained": true,
    "SingularValue": 34.487838306,
    "VarianceExplained": 0.0107009536
  },
  "w_comp_cor_19": {
    "CumulativeVarianceExplained": 0.3088408904,
    "Mask": "WM",
    "Method": "aCompCor",
    "Retained": true,
    "SingularValue": 34.3974698856,
    "VarianceExplained": 0.0106449477
  },
  "w_comp_cor_20": {
    "CumulativeVarianceExplained": 0.3194154688,
    "Mask": "WM",
    "Method": "aCompCor",
    "Retained": true,
    "SingularValue": 34.2835876872,
    "VarianceExplained": 0.0105745784
  },
  "w_comp_cor_21": {
    "CumulativeVarianceExplained": 0.3295978727,
    "Mask": "WM",
    "Method": "aCompCor",
    "Retained": true,
    "SingularValue": 33.6418518757,
    "VarianceExplained": 0.0101824039
  },
  "w_comp_cor_22": {
    "CumulativeVarianceExplained": 0.3397362325,
    "Mask": "WM",
    "Method": "aCompCor",
    "Retained": true,
    "SingularValue": 33.5690137732,
    "VarianceExplained": 0.0101383597
  },
  "w_comp_cor_23": {
    "CumulativeVarianceExplained": 0.3496645037,
    "Mask": "WM",
    "Method": "aCompCor",
    "Retained": true,
    "SingularValue": 33.2193821799,
    "VarianceExplained": 0.0099282713
  },
  "w_comp_cor_24": {
    "CumulativeVarianceExplained": 0.359507215,
    "Mask": "WM",
    "Method": "aCompCor",
    "Retained": true,
    "SingularValue": 33.0759332085,
    "VarianceExplained": 0.0098427113
  },
  "w_comp_cor_25": {
    "CumulativeVarianceExplained": 0.3692686086,
    "Mask": "WM",
    "Method": "aCompCor",
    "Retained": true,
    "SingularValue": 32.9390178333,
    "VarianceExplained": 0.0097613936
  },
  "w_comp_cor_26": {
    "CumulativeVarianceExplained": 0.3788659109,
    "Mask": "WM",
    "Method": "aCompCor",
    "Retained": true,
    "SingularValue": 32.6609883008,
    "VarianceExplained": 0.0095973024
  },
  "w_comp_cor_27": {
    "CumulativeVarianceExplained": 0.3883967999,
    "Mask": "WM",
    "Method": "aCompCor",
    "Retained": true,
    "SingularValue": 32.5477850061,
    "VarianceExplained": 0.009530889
  },
  "w_comp_cor_28": {
    "CumulativeVarianceExplained": 0.397876503,
    "Mask": "WM",
    "Method": "aCompCor",
    "Retained": true,
    "SingularValue": 32.4602680605,
    "VarianceExplained": 0.0094797031
  },
  "w_comp_cor_29": {
    "CumulativeVarianceExplained": 0.4072744455,
    "Mask": "WM",
    "Method": "aCompCor",
    "Retained": true,
    "SingularValue": 32.3199830037,
    "VarianceExplained": 0.0093979424
  },
  "w_comp_cor_30": {
    "CumulativeVarianceExplained": 0.4165302839,
    "Mask": "WM",
    "Method": "aCompCor",
    "Retained": true,
    "SingularValue": 32.0747009066,
    "VarianceExplained": 0.0092558384
  },
  "w_comp_cor_31": {
    "CumulativeVarianceExplained": 0.4256963318,
    "Mask": "WM",
    "Method": "aCompCor",
    "Retained": true,
    "SingularValue": 31.9187441764,
    "VarianceExplained": 0.009166048
  },
  "w_comp_cor_32": {
    "CumulativeVarianceExplained": 0.4347637738,
    "Mask": "WM",
    "Method": "aCompCor",
    "Retained": true,
    "SingularValue": 31.7465932201,
    "VarianceExplained": 0.009067442
  },
  "w_comp_cor_33": {
    "CumulativeVarianceExplained": 0.4436699078,
    "Mask": "WM",
    "Method": "aCompCor",
    "Retained": true,
    "SingularValue": 31.4629430528,
    "VarianceExplained": 0.0089061339
  },
  "w_comp_cor_34": {
    "CumulativeVarianceExplained": 0.4524153975,
    "Mask": "WM",
    "Method": "aCompCor",
    "Retained": true,
    "SingularValue": 31.1778957194,
    "VarianceExplained": 0.0087454897
  },
  "w_comp_cor_35": {
    "CumulativeVarianceExplained": 0.4611004279,
    "Mask": "WM",
    "Method": "aCompCor",
    "Retained": true,
    "SingularValue": 31.0699393223,
    "VarianceExplained": 0.0086850304
  },
  "w_comp_cor_36": {
    "CumulativeVarianceExplained": 0.4696502811,
    "Mask": "WM",
    "Method": "aCompCor",
    "Retained": true,
    "SingularValue": 30.8271987598,
    "VarianceExplained": 0.0085498532
  },
  "w_comp_cor_37": {
    "CumulativeVarianceExplained": 0.4781829488,
    "Mask": "WM",
    "Method": "aCompCor",
    "Retained": true,
    "SingularValue": 30.7962012476,
    "VarianceExplained": 0.0085326677
  },
  "w_comp_cor_38": {
    "CumulativeVarianceExplained": 0.4866274974,
    "Mask": "WM",
    "Method": "aCompCor",
    "Retained": true,
    "SingularValue": 30.6367685455,
    "VarianceExplained": 0.0084445487
  },
  "w_comp_cor_39": {
    "CumulativeVarianceExplained": 0.4948639111,
    "Mask": "WM",
    "Method": "aCompCor",
    "Retained": true,
    "SingularValue": 30.2568567885,
    "VarianceExplained": 0.0082364137
  },
  "w_comp_cor_40": {
    "CumulativeVarianceExplained": 0.5029784642,
    "Mask": "WM",
    "Method": "aCompCor",
    "Retained": true,
    "SingularValue": 30.0321922687,
    "VarianceExplained": 0.0081145531
  }
}